Workbook

Sheet STR Deal Analyzer
B1: ASCEND STR DEAL ANALYZER
B2: Short-Term Rental Investment Underwriting
B4: PROPERTY OVERVIEW & LINKS
B5: Property Address | E5: Analysis Date | F5: =TODAY()
B6: Listing Link (Redfin/Zillow) | E6: Market / City
B7: AirDNA Report Link | E7: Property Type
B8: Bedrooms | E8: Bathrooms
B9: Square Footage | E9: Year Built
B10: Lot Size | E10: Watch List / Amenities
B11: Notes
B13: PURCHASE DETAILS
B14: Purchase Price | E14: After Repair Value (ARV)
B15: Down Payment % | C15: 0.25 | E15: Down Payment $ | F15: =C14*C15
B16: Closing Cost % | C16: 0.01 | E16: Closing Costs $ | F16: =C14*C16
B17: Agent Commissions | C17: 0 | E17: Transaction Coordinator | F17: 0
B18: Total Cash to Close | C18: =F15+F16+C17+F17
B20: REHAB & SETUP COSTS
B21: Rehab / Renovation | C21: 0 | E21: Setup Expenses | F21: 3000
B22: Furnishings ($/sqft) | C22: 20 | E22: Furnishings & Guest Accesories Total | F22: =C9*C22
B23: Furnishings Override | E23: Leave blank to use $/sqft calc
B24: Legal | C24: 1000 | E24: STR Permits / Licenses | F24: 700
B25: Professional Photos / Staging | C25: 700
B26: Total Setup Costs | C26: =C21+F21+IF(C23>0,C23,F22)+C24+F24+C25
B28: FINANCING
B29: Loan Amount | C29: =C14-F15 | E29: Interest Rate | F29: 0.07
B30: Term (Years) | C30: 30 | E30: Interest Only? | F30: No
B31: Monthly Payment (P&I) | C31: =IF(F30="Yes",C29*F29/12,-PMT(F29/12,C30*12,C29)) | E31: PMI % | F31: 0
B32: Monthly PMI | C32: =C29*F31/12 | E32: Monthly PITI (est.) | F32: =C31+C32+C60/12+F60/12
B33: TOTAL CASH NEEDED | C33: =C18+C26
B35: STR REVENUE (from AirDNA)
B36: Average Daily Rate (ADR) | E36: Occupancy Rate (calendar, of 365)
B37: Active Days | C37: 365 | E37: Gross Revenue Override
B38: AirDNA Gross Revenue | C38: =IF(F37>0,F37,C36*C37*F36+C49) | E38: Gross = nightly + cleaning fees (matches AirROI). Cleaning nets out below.
B40: CHANNEL MIX & PLATFORM FEES | E40: Platform Fee Rate
B41: Airbnb (% of bookings) | C41: 0.7 | E41: Airbnb Host Fee | F41: 0.15
B42: VRBO (% of bookings) | C42: 0.15 | E42: VRBO Host Fee | F42: 0.07
B43: Booking.com (% of bookings) | C43: 0.1 | E43: Booking.com Commission | F43: 0.15
B44: Direct Booking (% of bookings) | C44: 0.05 | E44: Payment Processing Fee | F44: 0.029
B45: Blended OTA Fee Rate | C45: =C41*F41+C42*F42+C43*F43+C44*F44 | E45: Annual OTA Fees | F45: =C38*C45
B47: CLEANING COSTS
B48: Turnovers / Month | C48: 5 | E48: Cost Per Turnover | F48: 310
B49: Annual Cleaning Payouts | C49: =C48*F48*12 | E49: Cleaning is included in AirDNA revenue
B51: REVENUE WATERFALL
B52: AirDNA Gross Revenue | C52: =C38
B53: Less: OTA Platform Fees | C53: =-F45
B54: Less: Cleaning Payouts | C54: =-C49
B55: Host Accommodation Revenue | C55: =C52+C53+C54
B56: Management Fee % | C56: 0.15 | E56: Annual Management Fee $ | F56: =C55*C56
B57: Net Revenue to Owner | C57: =C55-F56
B59: FIXED EXPENSES
B60: Property Taxes (annual) | E60: Insurance (annual)
B61: HOA (annual) | E61: Debt Service (annual) | F61: =(C31+C32)*12
B62: Total Fixed Expenses | C62: =C60+F60+C61+F61
B64: VARIABLE OPERATING EXPENSES
B65: Repairs & Reserves (monthly) | C65: 200 | E65: Annual $ | F65: =C65*12
B66: Supplies (per turnover) | C66: 25 | E66: Annual $ | F66: =C66*C48*12
B67: Refunds & Guest Gifts (monthly) | C67: 50 | E67: Annual $ | F67: =C67*12
B68: Utilities (monthly) | C68: 250 | E68: Annual $ | F68: =C68*12
B69: Internet (monthly) | C69: 100 | E69: Annual $ | F69: =C69*12
B70: Landscaping / Snow (monthly) | C70: 250 | E70: Annual $ | F70: =C70*12
B71: Hot Tub / Pool Maintenance (monthly) | C71: 0 | E71: Annual $ | F71: =C71*12
B72: Total Variable Expenses | C72: =SUM(F65:F71)
B73: OpEx as % of Host Accomm Rev | C73: =IF(C55>0,(F56+C72+C60+F60+C61)/C55,0)
B75: TOTAL EXPENSES & CASH FLOW
B76: Net Revenue to Owner | C76: =C57
B77: Less: Fixed Expenses (Tax+Ins+HOA) | C77: =C60+F60+C61
B78: Less: Variable Operating Expenses | C78: =C72
B79: NOI (Net Operating Income) | C79: =C76-C77-C78
B80: Less: Annual Debt Service | C80: =F61
B81: Pre-Tax Cash Flow (annual) | C81: =C79-C80
B82: Monthly Cash Flow | C82: =C81/12
B84: TAX DEDUCTIONS & DEPRECIATION
B85: Effective Tax Bracket | C85: 0.35 | E85: Land Value (% of purchase) | F85: 0.2
B86: Land Value ($) | C86: =C14*F85 | E86: Building Value ($) | F86: =IF(F14>0,F14-C86,C14-C86)
B87: Annual Depreciation (27.5 yr) | C87: =F86/27.5
B88: Year 1 Interest (approx) | C88: =C29*F29 | E88: Year 1 Principal Paydown | F88: =F61-C88
B89: Deductible Startup Costs (Yr 1) | C89: =MIN(C26,5000) | E89: IRS allows $5K in Year 1, rest over 15yr
B90: Taxable Rental Income | C90: =C79-C88-C87-C89
B91: Tax Owed (if positive) | C91: =IF(C90>0,C90*C85,0)
B92: Post-Tax Cash Flow (Year 1) | C92: =C81-C91
B93: Tax Savings from Depreciation | C93: =C87*C85
B95: ESTIMATED YEAR 1 BONUS DEPRECIATION TAX BENEFIT
B96: Tax Write-Off Estimate (Low) | C96: =MIN((C14*0.1)*2, (C14-(C14*0.25))*0.25) | E96: Tax Write-Off Estimate (High) | F96: =MAX((C14*0.1)*2, (C14-(C14*0.25))*0.25)
B97: Year 1 Tax Savings (Low) | C97: =C96*C85 | E97: Year 1 Tax Savings (High) | F97: =F96*C85
B99: Post-Tax CF with Write-Off (Low) | C99: =C81+C97 | E99: Post-Tax CF with Write-Off (High) | F99: =C81+F97
B100: Monthly CF with Write-Off (Low) | C100: =C99/12 | E100: Monthly CF with Write-Off (High) | F100: =F99/12
B101: Post-Tax COC with Write-Off (Low) | C101: =IF(C33>0,C99/C33,0) | E101: Post-Tax COC with Write-Off (High) | F101: =IF(C33>0,F99/C33,0)
B105: KEY RETURN METRICS
B106: Cash-on-Cash Return (Pre-Tax) | C106: =IF(C33>0,C81/C33,0)
B107: Post-Tax CoC Return | C107: =IF(C33>0,(C92+C93)/C33,0)
B108: Cap Rate | C108: =IF(C14>0,C79/C14,0) | E108: Debt Service Coverage (DSCR) | F108: =IF(F61>0,C79/F61,0)
B109: Return on Equity | C109: =IF((IF(F14>0,F14,C14)-C29)>0,C81/(IF(F14>0,F14,C14)-C29),0) | E109: Gross Rent Multiplier (GRM) | F109: =IF(C38>0,C14/C38,0)
B110: Break-Even Occupancy | C110: =IF(C38>0,(C60+F60+C61+F61+F65+F67+F68+F69+F70+F71)*F36/(C38-F45-C49-F56-F66),0) | E110: 6 Months Reserve Needed | F110: =F32*6
B111: Payback Period (months) | C111: =IF(C82>0,ROUND(C33/C82,0),"N/A")

Sheet Renovation Calculator
A1: ASCEND · RENOVATION CALCULATOR
A2: Blue cells = your inputs. Scope defaults to Mid. Amenities: change "Include?" to Yes to add to estimate. Update rates anytime on the Rates tab.
A4: Total Home Square Footage | B4: ='STR Deal Analyzer'!C9 | C4: sqft
A6: 01 · FLOORING
A7: ITEM | B7: QUANTITY | C7: UNIT | D7: SCOPE | E7: RATE ($/UNIT) | F7: LINE TOTAL
A8: LVP Flooring | C8: sqft | D8: Mid | E8: 5 | F8: =IF(OR(B8="",B8=0),0,B8*E8)
A9: Tile Flooring | C9: sqft | D9: Mid | E9: {=IFERROR(INDEX('Renovation Rates'!$B:$D,MATCH(A9,'Renovation Rates'!$A:$A,0),IF(D9="Low",1,IF(D9="Mid",2,3))),0)} | F9: =IF(OR(B9="",B9=0),0,B9*E9)
A10: Carpet | C10: sqft | D10: Mid | E10: {=IFERROR(INDEX('Renovation Rates'!$B:$D,MATCH(A10,'Renovation Rates'!$A:$A,0),IF(D10="Low",1,IF(D10="Mid",2,3))),0)} | F10: =IF(OR(B10="",B10=0),0,B10*E10)
A11: FLOORING SUBTOTAL | F11: =SUM(F8:F10)
A13: 02 · INTERIOR PAINT
A14: ITEM | B14: QUANTITY | C14: UNIT | D14: SCOPE | E14: RATE ($/UNIT) | F14: LINE TOTAL
A15: Paint - Walls Only | C15: sqft | D15: Mid | E15: {=IFERROR(INDEX('Renovation Rates'!$B:$D,MATCH(A15,'Renovation Rates'!$A:$A,0),IF(D15="Low",1,IF(D15="Mid",2,3))),0)} | F15: =IF(OR(B15="",B15=0),0,B15*E15)
A16: Paint - Walls + Ceilings + Trim | C16: sqft | D16: High | E16: {=IFERROR(INDEX('Renovation Rates'!$B:$D,MATCH(A16,'Renovation Rates'!$A:$A,0),IF(D16="Low",1,IF(D16="Mid",2,3))),0)} | F16: =IF(OR(B16="",B16=0),0,B16*E16)
A17: PAINT SUBTOTAL | F17: =SUM(F15:F16)
A19: 03 · KITCHEN
A20: ITEM | B20: QUANTITY | C20: UNIT | D20: SCOPE | E20: RATE (FLAT) | F20: LINE TOTAL
A21: Kitchen - Refresh | B21: 0 | C21: flat | D21: Mid | E21: {=IFERROR(INDEX('Renovation Rates'!$B:$D,MATCH(A21,'Renovation Rates'!$A:$A,0),IF(D21="Low",1,IF(D21="Mid",2,3))),0)} | F21: =IF(OR(B21="",B21=0),0,B21*E21)
A22: Kitchen - Partial Remodel | B22: 0 | C22: flat | D22: Mid | E22: {=IFERROR(INDEX('Renovation Rates'!$B:$D,MATCH(A22,'Renovation Rates'!$A:$A,0),IF(D22="Low",1,IF(D22="Mid",2,3))),0)} | F22: =IF(OR(B22="",B22=0),0,B22*E22)
A23: Kitchen - Full Remodel | B23: 0 | C23: flat | D23: Mid | E23: {=IFERROR(INDEX('Renovation Rates'!$B:$D,MATCH(A23,'Renovation Rates'!$A:$A,0),IF(D23="Low",1,IF(D23="Mid",2,3))),0)} | F23: =IF(OR(B23="",B23=0),0,B23*E23)
A24: KITCHEN SUBTOTAL | F24: =SUM(F21:F23)
A26: 04 · BATHROOMS
A27: ITEM | B27: # OF BATHS | C27: UNIT | D27: SCOPE | E27: RATE (PER BATH) | F27: LINE TOTAL
A28: Bathroom - Refresh | B28: 0 | C28: per bath | D28: Mid | E28: {=IFERROR(INDEX('Renovation Rates'!$B:$D,MATCH(A28,'Renovation Rates'!$A:$A,0),IF(D28="Low",1,IF(D28="Mid",2,3))),0)} | F28: =IF(OR(B28="",B28=0),0,B28*E28)
A29: Bathroom - Mid Remodel | B29: 0 | C29: per bath | D29: Mid | E29: {=IFERROR(INDEX('Renovation Rates'!$B:$D,MATCH(A29,'Renovation Rates'!$A:$A,0),IF(D29="Low",1,IF(D29="Mid",2,3))),0)} | F29: =IF(OR(B29="",B29=0),0,B29*E29)
A30: Bathroom - Full Gut | B30: 0 | C30: per bath | D30: Mid | E30: {=IFERROR(INDEX('Renovation Rates'!$B:$D,MATCH(A30,'Renovation Rates'!$A:$A,0),IF(D30="Low",1,IF(D30="Mid",2,3))),0)} | F30: =IF(OR(B30="",B30=0),0,B30*E30)
A31: BATHROOMS SUBTOTAL | F31: =SUM(F28:F30)
A33: 05 · MECHANICAL SYSTEMS
A34: ITEM | B34: QTY (1 = Replace) | C34: UNIT | D34: SCOPE | E34: RATE | F34: LINE TOTAL
A35: HVAC - Full Replacement | B35: 0 | C35: flat | D35: Mid | E35: {=IFERROR(INDEX('Renovation Rates'!$B:$D,MATCH(A35,'Renovation Rates'!$A:$A,0),IF(D35="Low",1,IF(D35="Mid",2,3))),0)} | F35: =IF(OR(B35="",B35=0),0,B35*E35)
A36: Mini-Split (per Zone) | B36: 0 | C36: per zone | D36: Mid | E36: {=IFERROR(INDEX('Renovation Rates'!$B:$D,MATCH(A36,'Renovation Rates'!$A:$A,0),IF(D36="Low",1,IF(D36="Mid",2,3))),0)} | F36: =IF(OR(B36="",B36=0),0,B36*E36)
A37: Water Heater - Tank | B37: 0 | C37: flat | D37: Mid | E37: {=IFERROR(INDEX('Renovation Rates'!$B:$D,MATCH(A37,'Renovation Rates'!$A:$A,0),IF(D37="Low",1,IF(D37="Mid",2,3))),0)} | F37: =IF(OR(B37="",B37=0),0,B37*E37)
A38: Water Heater - Tankless | B38: 0 | C38: flat | D38: Mid | E38: {=IFERROR(INDEX('Renovation Rates'!$B:$D,MATCH(A38,'Renovation Rates'!$A:$A,0),IF(D38="Low",1,IF(D38="Mid",2,3))),0)} | F38: =IF(OR(B38="",B38=0),0,B38*E38)
A39: Electrical Panel Upgrade | B39: 0 | C39: flat | D39: Mid | E39: {=IFERROR(INDEX('Renovation Rates'!$B:$D,MATCH(A39,'Renovation Rates'!$A:$A,0),IF(D39="Low",1,IF(D39="Mid",2,3))),0)} | F39: =IF(OR(B39="",B39=0),0,B39*E39)
A40: MECHANICAL SUBTOTAL | F40: =SUM(F35:F39)
A42: 06 · DOORS, WINDOWS & LIGHTING
A43: ITEM | B43: COUNT | C43: UNIT | D43: SCOPE | E43: RATE (EACH) | F43: LINE TOTAL
A44: Interior Door | B44: 0 | C44: each | D44: Mid | E44: {=IFERROR(INDEX('Renovation Rates'!$B:$D,MATCH(A44,'Renovation Rates'!$A:$A,0),IF(D44="Low",1,IF(D44="Mid",2,3))),0)} | F44: =IF(OR(B44="",B44=0),0,B44*E44)
A45: Exterior Door | B45: 0 | C45: each | D45: Mid | E45: {=IFERROR(INDEX('Renovation Rates'!$B:$D,MATCH(A45,'Renovation Rates'!$A:$A,0),IF(D45="Low",1,IF(D45="Mid",2,3))),0)} | F45: =IF(OR(B45="",B45=0),0,B45*E45)
A46: Window Replacement | B46: 0 | C46: each | D46: Mid | E46: {=IFERROR(INDEX('Renovation Rates'!$B:$D,MATCH(A46,'Renovation Rates'!$A:$A,0),IF(D46="Low",1,IF(D46="Mid",2,3))),0)} | F46: =IF(OR(B46="",B46=0),0,B46*E46)
A47: Light Fixture | B47: 0 | C47: each | D47: Mid | E47: {=IFERROR(INDEX('Renovation Rates'!$B:$D,MATCH(A47,'Renovation Rates'!$A:$A,0),IF(D47="Low",1,IF(D47="Mid",2,3))),0)} | F47: =IF(OR(B47="",B47=0),0,B47*E47)
A48: DOORS / WINDOWS / LIGHTING SUBTOTAL | F48: =SUM(F44:F47)
A50: 07 · EXTERIOR & CURB APPEAL
A51: ITEM | B51: QUANTITY | C51: UNIT | D51: SCOPE | E51: RATE ($/UNIT) | F51: LINE TOTAL
A52: Exterior Paint | B52: 0 | C52: 2843 | D52: Mid | E52: {=IFERROR(INDEX('Renovation Rates'!$B:$D,MATCH(A52,'Renovation Rates'!$A:$A,0),IF(D52="Low",1,IF(D52="Mid",2,3))),0)} | F52: =IF(OR(B52="",B52=0),0,B52*E52)
A53: Landscaping Refresh | B53: 0 | C53: flat | D53: High | E53: {=IFERROR(INDEX('Renovation Rates'!$B:$D,MATCH(A53,'Renovation Rates'!$A:$A,0),IF(D53="Low",1,IF(D53="Mid",2,3))),0)} | F53: =IF(OR(B53="",B53=0),0,B53*E53)
A54: Driveway Reseal / Repair | B54: 0 | C54: flat | D54: Mid | E54: {=IFERROR(INDEX('Renovation Rates'!$B:$D,MATCH(A54,'Renovation Rates'!$A:$A,0),IF(D54="Low",1,IF(D54="Mid",2,3))),0)} | F54: =IF(OR(B54="",B54=0),0,B54*E54)
A55: New Sod | B55: 0 | C55: sqft | D55: Mid | E55: {=IFERROR(INDEX('Renovation Rates'!$B:$D,MATCH(A55,'Renovation Rates'!$A:$A,0),IF(D55="Low",1,IF(D55="Mid",2,3))),0)} | F55: =IF(OR(B55="",B55=0),0,B55*E55)
A56: Fencing | B56: 0 | C56: linear ft | D56: Mid | E56: {=IFERROR(INDEX('Renovation Rates'!$B:$D,MATCH(A56,'Renovation Rates'!$A:$A,0),IF(D56="Low",1,IF(D56="Mid",2,3))),0)} | F56: =IF(OR(B56="",B56=0),0,B56*E56)
A57: EXTERIOR SUBTOTAL | F57: =SUM(F52:F56)
A59: 08 · STR AMENITY ADD-ONS
A60: AMENITY | B60: INCLUDE? | C60: UNIT | D60: SCOPE | E60: RATE | F60: LINE TOTAL
A61: Hot Tub | B61: No | C61: flat | D61: Low | E61: {=IFERROR(INDEX('Renovation Rates'!$B:$D,MATCH(A61,'Renovation Rates'!$A:$A,0),IF(D61="Low",1,IF(D61="Mid",2,3))),0)} | F61: =IF(B61="Yes",E61,0)
A62: Pool - Fiberglass Inground | B62: No | C62: flat | D62: Mid | E62: {=IFERROR(INDEX('Renovation Rates'!$B:$D,MATCH(A62,'Renovation Rates'!$A:$A,0),IF(D62="Low",1,IF(D62="Mid",2,3))),0)} | F62: =IF(B62="Yes",E62,0)
A63: Pool - Gunite / Concrete | B63: No | C63: flat | D63: Mid | E63: {=IFERROR(INDEX('Renovation Rates'!$B:$D,MATCH(A63,'Renovation Rates'!$A:$A,0),IF(D63="Low",1,IF(D63="Mid",2,3))),0)} | F63: =IF(B63="Yes",E63,0)
A64: Plunge Pool | B64: No | C64: flat | D64: Mid | E64: {=IFERROR(INDEX('Renovation Rates'!$B:$D,MATCH(A64,'Renovation Rates'!$A:$A,0),IF(D64="Low",1,IF(D64="Mid",2,3))),0)} | F64: =IF(B64="Yes",E64,0)
A65: Volleyball Sand Court | B65: No | C65: flat | D65: Mid | E65: {=IFERROR(INDEX('Renovation Rates'!$B:$D,MATCH(A65,'Renovation Rates'!$A:$A,0),IF(D65="Low",1,IF(D65="Mid",2,3))),0)} | F65: =IF(B65="Yes",E65,0)
A66: Fire Pit - Prefab | B66: No | C66: flat | D66: Mid | E66: {=IFERROR(INDEX('Renovation Rates'!$B:$D,MATCH(A66,'Renovation Rates'!$A:$A,0),IF(D66="Low",1,IF(D66="Mid",2,3))),0)} | F66: =IF(B66="Yes",E66,0)
A67: Fire Pit - Built-In Stone | B67: No | C67: flat | D67: Mid | E67: {=IFERROR(INDEX('Renovation Rates'!$B:$D,MATCH(A67,'Renovation Rates'!$A:$A,0),IF(D67="Low",1,IF(D67="Mid",2,3))),0)} | F67: =IF(B67="Yes",E67,0)
A68: Outdoor Kitchen - Basic | B68: No | C68: flat | D68: Mid | E68: {=IFERROR(INDEX('Renovation Rates'!$B:$D,MATCH(A68,'Renovation Rates'!$A:$A,0),IF(D68="Low",1,IF(D68="Mid",2,3))),0)} | F68: =IF(B68="Yes",E68,0)
A69: Outdoor Kitchen - Full | B69: No | C69: flat | D69: Mid | E69: {=IFERROR(INDEX('Renovation Rates'!$B:$D,MATCH(A69,'Renovation Rates'!$A:$A,0),IF(D69="Low",1,IF(D69="Mid",2,3))),0)} | F69: =IF(B69="Yes",E69,0)
A70: Pergola - Prefab Kit | B70: No | C70: flat | D70: Mid | E70: {=IFERROR(INDEX('Renovation Rates'!$B:$D,MATCH(A70,'Renovation Rates'!$A:$A,0),IF(D70="Low",1,IF(D70="Mid",2,3))),0)} | F70: =IF(B70="Yes",E70,0)
A71: Pergola - Custom Built | B71: No | C71: flat | D71: Mid | E71: {=IFERROR(INDEX('Renovation Rates'!$B:$D,MATCH(A71,'Renovation Rates'!$A:$A,0),IF(D71="Low",1,IF(D71="Mid",2,3))),0)} | F71: =IF(B71="Yes",E71,0)
A72: Game Room Setup | B72: Yes | C72: flat | D72: Mid | E72: {=IFERROR(INDEX('Renovation Rates'!$B:$D,MATCH(A72,'Renovation Rates'!$A:$A,0),IF(D72="Low",1,IF(D72="Mid",2,3))),0)} | F72: =IF(B72="Yes",E72,0)
A73: Putting Green (Artificial Turf) | B73: No | C73: flat | D73: Mid | E73: {=IFERROR(INDEX('Renovation Rates'!$B:$D,MATCH(A73,'Renovation Rates'!$A:$A,0),IF(D73="Low",1,IF(D73="Mid",2,3))),0)} | F73: =IF(B73="Yes",E73,0)
A74: AMENITIES SUBTOTAL | F74: =SUM(F61:F73)
A76: 09 · SOFT COSTS
A77: ITEM | B77: AMOUNT / RATE | C77: UNIT | F77: LINE TOTAL
A78: Permits (estimated) | B78: 2200 | C78: flat | F78: 0
A79: Contingency (% of hard costs) | B79: 0.12 | C79: % | F79: =(F11+F17+F24+F31+F40+F48+F57+F74)*B79
A80: SOFT COSTS SUBTOTAL | F80: =SUM(F78:F79)
A82: ESTIMATE SUMMARY
A83: Total Hard Costs (Sections 01–08) | F83: =F11+F17+F24+F31+F40+F48+F57+F74
A84: Total Soft Costs (Permits + Contingency) | F84: =F80
A85: TOTAL RENOVATION BUDGET | F85: =F83+F84
A86: Estimated Cost per Sqft | F86: =IFERROR(F85/B4,0)

Sheet Renovation Rates
A1: ITEM NAME | B1: LOW ($) | C1: MID ($) | D1: HIGH ($) | E1: UNIT / SCOPE NOTES
A2: Item names must match exactly what appears in the Estimator tab. All rates are blended averages — update as your market data evolves.
A3: ── FLOORING ──
A4: LVP Flooring | B4: 4 | C4: 5.5 | D4: 7 | E4: $/sqft installed — low=basic, high=premium pattern
A5: Tile Flooring | B5: 7 | C5: 10 | D5: 14 | E5: $/sqft installed — low=standard, high=complex layout
A6: Carpet | B6: 3 | C6: 4 | D6: 5 | E6: $/sqft installed — low=budget, high=quality pad+carpet
A7: ── INTERIOR PAINT ──
A8: Paint - Walls Only | B8: 1.5 | C8: 1.75 | D8: 2 | E8: $/sqft of home living area
A9: Paint - Walls + Ceilings + Trim | B9: 2.5 | C9: 3 | D9: 3.5 | E9: $/sqft of home living area
A10: ── KITCHEN ──
A11: Kitchen - Refresh | B11: 3000 | C11: 4500 | D11: 6000 | E11: Flat / paint cabs, new hardware, new countertops
A12: Kitchen - Partial Remodel | B12: 8000 | C12: 11000 | D12: 14000 | E12: Flat / new counters + appliances, keep cabinet boxes
A13: Kitchen - Full Remodel | B13: 18000 | C13: 26500 | D13: 35000 | E13: Flat / new cabs, counters, appliances, backsplash
A14: ── BATHROOMS ──
A15: Bathroom - Refresh | B15: 2000 | C15: 3000 | D15: 4000 | E15: Per bath / vanity, toilet, fixtures, paint
A16: Bathroom - Mid Remodel | B16: 6000 | C16: 9000 | D16: 12000 | E16: Per bath / tile surround, new vanity, toilet
A17: Bathroom - Full Gut | B17: 12000 | C17: 16000 | D17: 20000 | E17: Per bath / complete gut and rebuild
A18: ── MECHANICAL SYSTEMS ──
A19: HVAC - Full Replacement | B19: 7000 | C19: 10000 | D19: 13000 | E19: Flat / central air + heat replacement
A20: Mini-Split (per Zone) | B20: 3000 | C20: 4500 | D20: 6000 | E20: Per zone installed / good for additions or garages
A21: Water Heater - Tank | B21: 1200 | C21: 1850 | D21: 2500 | E21: Flat installed
A22: Water Heater - Tankless | B22: 2800 | C22: 3900 | D22: 5000 | E22: Flat installed
A23: Electrical Panel Upgrade | B23: 2500 | C23: 3750 | D23: 5000 | E23: Flat / 100A → 200A service upgrade
A24: ── DOORS, WINDOWS & LIGHTING ──
A25: Interior Door | B25: 250 | C25: 350 | D25: 450 | E25: Per door installed (slab + hardware + install)
A26: Exterior Door | B26: 1000 | C26: 1750 | D26: 2500 | E26: Per door installed (entry-grade to premium)
A27: Window Replacement | B27: 500 | C27: 700 | D27: 900 | E27: Per window installed / standard double-pane
A28: Light Fixture | B28: 150 | C28: 250 | D28: 350 | E28: Per fixture installed (basic to designer)
A29: ── EXTERIOR & CURB APPEAL ──
A30: Exterior Paint | B30: 1 | C30: 1.75 | D30: 2.5 | E30: $/sqft of home living area
A31: Landscaping Refresh | B31: 500 | C31: 2000 | D31: 3500 | E31: Flat / cleanup, mulch, shrubs, edging
A32: Driveway Reseal / Repair | B32: 500 | C32: 1250 | D32: 2000 | E32: Flat / patch, resurface, seal
A33: New Sod | B33: 1.5 | C33: 2.25 | D33: 3 | E33: $/sqft installed / including grading and soil prep
A34: Fencing | B34: 15 | C34: 25 | D34: 35 | E34: $/linear ft installed (wood = low, vinyl = high)
A35: ── STR AMENITY ADD-ONS ──
A36: Hot Tub | B36: 7000 | C36: 14000 | D36: 22000 | E36: Flat / electrical, concrete pad, unit
A37: Pool - Fiberglass Inground | B37: 45000 | C37: 65000 | D37: 85000 | E37: Flat / shell, excavation, plumbing, equipment
A38: Pool - Gunite / Concrete | B38: 60000 | C38: 85000 | D38: 110000 | E38: Flat / custom concrete, longer install timeline
A39: Plunge Pool | B39: 25000 | C39: 35000 | D39: 50000 | E39: Flat / smaller footprint, good for tight lots
A40: Volleyball Sand Court | B40: 1500 | C40: 3500 | D40: 7000 | E40: Flat / high end includes drainage, posts, net, border
A41: Fire Pit - Prefab | B41: 500 | C41: 1000 | D41: 2000 | E41: Flat / prefab unit + basic patio installation
A42: Fire Pit - Built-In Stone | B42: 2000 | C42: 4000 | D42: 7000 | E42: Flat / custom masonry, gas or wood
A43: Outdoor Kitchen - Basic | B43: 3000 | C43: 6000 | D43: 10000 | E43: Flat / grill, counter surface, basic hookups
A44: Outdoor Kitchen - Full | B44: 10000 | C44: 17000 | D44: 25000 | E44: Flat / grill, fridge, sink, bar seating, shade
A45: Pergola - Prefab Kit | B45: 3000 | C45: 5500 | D45: 9000 | E45: Flat / kit assembly + concrete footings
A46: Pergola - Custom Built | B46: 8000 | C46: 13000 | D46: 20000 | E46: Flat / custom lumber, posts, roof panels
A47: Game Room Setup | B47: 3500 | C47: 5000 | D47: 11000 | E47: Flat / pool table, foosball, seating, lighting, TV, game console, Basketball hoop, poker table
A48: Putting Green (Artificial Turf) | B48: 5000 | C48: 9000 | D48: 15000 | E48: Flat / turf, framing, cups, border edging

Sheet Long-Term Outlook
B1: LONG-TERM OUTLOOK — 10 YEAR PROJECTION
B3: ASSUMPTIONS
B4: Annual Income Increase | C4: 0.03 | D4: Annual Expense Increase | E4: 0.03 | G4: Annual Appreciation | H4: 0.03 | J4: Selling Costs % | K4: 0.07
B6: Year | C6: 1 | D6: 2 | E6: 3 | F6: 4 | G6: 5 | H6: 6 | I6: 7 | J6: 8 | K6: 9 | L6: 10
B7: INCOME
B8: Gross Revenue | C8: ='STR Deal Analyzer'!C38 | D8: =C8*(1+$C$4) | E8: =D8*(1+$C$4) | F8: =E8*(1+$C$4) | G8: =F8*(1+$C$4) | H8: =G8*(1+$C$4) | I8: =H8*(1+$C$4) | J8: =I8*(1+$C$4) | K8: =J8*(1+$C$4) | L8: =K8*(1+$C$4)
B9: OTA Fees | C9: ='STR Deal Analyzer'!F45 | D9: =C9*(1+$C$4) | E9: =D9*(1+$C$4) | F9: =E9*(1+$C$4) | G9: =F9*(1+$C$4) | H9: =G9*(1+$C$4) | I9: =H9*(1+$C$4) | J9: =I9*(1+$C$4) | K9: =J9*(1+$C$4) | L9: =K9*(1+$C$4)
B10: Cleaning Payouts | C10: ='STR Deal Analyzer'!C49 | D10: =C10*(1+$E$4) | E10: =D10*(1+$E$4) | F10: =E10*(1+$E$4) | G10: =F10*(1+$E$4) | H10: =G10*(1+$E$4) | I10: =H10*(1+$E$4) | J10: =I10*(1+$E$4) | K10: =J10*(1+$E$4) | L10: =K10*(1+$E$4)
B11: Host Accommodation Revenue | C11: =C8-C9-C10 | D11: =D8-D9-D10 | E11: =E8-E9-E10 | F11: =F8-F9-F10 | G11: =G8-G9-G10 | H11: =H8-H9-H10 | I11: =I8-I9-I10 | J11: =J8-J9-J10 | ... L11: =L8-L9-L10
B12: Management Fee | C12: ='STR Deal Analyzer'!F56 | D12: =D11*'STR Deal Analyzer'!C56 | E12: =E11*'STR Deal Analyzer'!C56 | F12: =F11*'STR Deal Analyzer'!C56 | G12: =G11*'STR Deal Analyzer'!C56 | H12: =H11*'STR Deal Analyzer'!C56 | I12: =I11*'STR Deal Analyzer'!C56 | J12: =J11*'STR Deal Analyzer'!C56 | K12: =K11*'STR Deal Analyzer'!C56 | L12: =L11*'STR Deal Analyzer'!C56
B13: Net Revenue to Owner | C13: =C11-C12 | D13: =D11-D12 | E13: =E11-E12 | F13: =F11-F12 | G13: =G11-G12 | H13: =H11-H12 | I13: =I11-I12 | J13: =J11-J12 | ... L13: =L11-L12
B15: OPERATING EXPENSES
B16: Fixed (Tax+Ins+HOA) | C16: ='STR Deal Analyzer'!C60+'STR Deal Analyzer'!F60+'STR Deal Analyzer'!C61 | D16: =C16*(1+$E$4) | E16: =D16*(1+$E$4) | F16: =E16*(1+$E$4) | G16: =F16*(1+$E$4) | H16: =G16*(1+$E$4) | I16: =H16*(1+$E$4) | J16: =I16*(1+$E$4) | K16: =J16*(1+$E$4) | L16: =K16*(1+$E$4)
B17: Variable Operating | C17: ='STR Deal Analyzer'!C72 | D17: =C17*(1+$E$4) | E17: =D17*(1+$E$4) | F17: =E17*(1+$E$4) | G17: =F17*(1+$E$4) | H17: =G17*(1+$E$4) | I17: =H17*(1+$E$4) | J17: =I17*(1+$E$4) | K17: =J17*(1+$E$4) | L17: =K17*(1+$E$4)
B18: Total Operating Expenses | C18: =C16+C17 | D18: =D16+D17 | E18: =E16+E17 | F18: =F16+F17 | G18: =G16+G17 | H18: =H16+H17 | I18: =I16+I17 | J18: =J16+J17 | ... L18: =L16+L17
B20: CASH FLOW
B21: NOI | C21: =C13-C18 | D21: =D13-D18 | E21: =E13-E18 | F21: =F13-F18 | G21: =G13-G18 | H21: =H13-H18 | I21: =I13-I18 | J21: =J13-J18 | ... L21: =L13-L18
B22: Loan Payments | C22: ='STR Deal Analyzer'!F61 | D22: =C22 | E22: =C22 | F22: =C22 | G22: =C22 | H22: =C22 | I22: =C22 | J22: =C22 | K22: =C22 | L22: =C22
B23: Pre-Tax Cash Flow | C23: =C21-C22 | D23: =D21-D22 | E23: =E21-E22 | F23: =F21-F22 | G23: =G21-G22 | H23: =H21-H22 | I23: =I21-I22 | J23: =J21-J22 | ... L23: =L21-L22
B24: Cumulative Pre-Tax CF | C24: =C23 | D24: =C24+D23 | E24: =D24+E23 | F24: =E24+F23 | G24: =F24+G23 | H24: =G24+H23 | I24: =H24+I23 | J24: =I24+J23 | K24: =J24+K23 | L24: =K24+L23
B26: TAX DEDUCTIONS
B27: Annual Depreciation | C27: ='STR Deal Analyzer'!C87 | D27: =C27 | E27: =C27 | F27: =C27 | G27: =C27 | H27: =C27 | I27: =C27 | J27: =C27 | K27: =C27 | L27: =C27
B29: EQUITY & SALE ANALYSIS
B30: Property Value | C30: =IF('STR Deal Analyzer'!F14>0,'STR Deal Analyzer'!F14,'STR Deal Analyzer'!C14)*(1+$H$4) | D30: =C30*(1+$H$4) | E30: =D30*(1+$H$4) | F30: =E30*(1+$H$4) | G30: =F30*(1+$H$4) | H30: =G30*(1+$H$4) | I30: =H30*(1+$H$4) | J30: =I30*(1+$H$4) | K30: =J30*(1+$H$4) | L30: =K30*(1+$H$4)
B31: Loan Balance (approx) | C31: =IF('STR Deal Analyzer'!C29>0,-PV('STR Deal Analyzer'!F29/12,'STR Deal Analyzer'!C30*12-12,-PMT('STR Deal Analyzer'!F29/12,'STR Deal Analyzer'!C30*12,'STR Deal Analyzer'!C29)),0) | D31: =IF('STR Deal Analyzer'!C29>0,-PV('STR Deal Analyzer'!F29/12,'STR Deal Analyzer'!C30*12-24,-PMT('STR Deal Analyzer'!F29/12,'STR Deal Analyzer'!C30*12,'STR Deal Analyzer'!C29)),0) | E31: =IF('STR Deal Analyzer'!C29>0,-PV('STR Deal Analyzer'!F29/12,'STR Deal Analyzer'!C30*12-36,-PMT('STR Deal Analyzer'!F29/12,'STR Deal Analyzer'!C30*12,'STR Deal Analyzer'!C29)),0) | F31: =IF('STR Deal Analyzer'!C29>0,-PV('STR Deal Analyzer'!F29/12,'STR Deal Analyzer'!C30*12-48,-PMT('STR Deal Analyzer'!F29/12,'STR Deal Analyzer'!C30*12,'STR Deal Analyzer'!C29)),0) | G31: =IF('STR Deal Analyzer'!C29>0,-PV('STR Deal Analyzer'!F29/12,'STR Deal Analyzer'!C30*12-60,-PMT('STR Deal Analyzer'!F29/12,'STR Deal Analyzer'!C30*12,'STR Deal Analyzer'!C29)),0) | H31: =IF('STR Deal Analyzer'!C29>0,-PV('STR Deal Analyzer'!F29/12,'STR Deal Analyzer'!C30*12-72,-PMT('STR Deal Analyzer'!F29/12,'STR Deal Analyzer'!C30*12,'STR Deal Analyzer'!C29)),0) | I31: =IF('STR Deal Analyzer'!C29>0,-PV('STR Deal Analyzer'!F29/12,'STR Deal Analyzer'!C30*12-84,-PMT('STR Deal Analyzer'!F29/12,'STR Deal Analyzer'!C30*12,'STR Deal Analyzer'!C29)),0) | J31: =IF('STR Deal Analyzer'!C29>0,-PV('STR Deal Analyzer'!F29/12,'STR Deal Analyzer'!C30*12-96,-PMT('STR Deal Analyzer'!F29/12,'STR Deal Analyzer'!C30*12,'STR Deal Analyzer'!C29)),0) | K31: =IF('STR Deal Analyzer'!C29>0,-PV('STR Deal Analyzer'!F29/12,'STR Deal Analyzer'!C30*12-108,-PMT('STR Deal Analyzer'!F29/12,'STR Deal Analyzer'!C30*12,'STR Deal Analyzer'!C29)),0) | L31: =IF('STR Deal Analyzer'!C29>0,-PV('STR Deal Analyzer'!F29/12,'STR Deal Analyzer'!C30*12-120,-PMT('STR Deal Analyzer'!F29/12,'STR Deal Analyzer'!C30*12,'STR Deal Analyzer'!C29)),0)
B32: Net Equity | C32: =C30-C31 | D32: =D30-D31 | E32: =E30-E31 | F32: =F30-F31 | G32: =G30-G31 | H32: =H30-H31 | I32: =I30-I31 | J32: =J30-J31 | ... L32: =L30-L31
B34: Selling Costs | C34: =-C30*$K$4 | D34: =-D30*$K$4 | E34: =-E30*$K$4 | F34: =-F30*$K$4 | G34: =-G30*$K$4 | H34: =-H30*$K$4 | I34: =-I30*$K$4 | J34: =-J30*$K$4 | ... L34: =-L30*$K$4
B35: Net Sale Proceeds | C35: =C32+C34 | D35: =D32+D34 | E35: =E32+E34 | F35: =F32+F34 | G35: =G32+G34 | H35: =H32+H34 | I35: =I32+I34 | J35: =J32+J34 | ... L35: =L32+L34
B37: INVESTMENT RETURNS
B38: Cap Rate (Purchase Price) | C38: =IF('STR Deal Analyzer'!C14>0,C21/'STR Deal Analyzer'!C14,0) | D38: =IF('STR Deal Analyzer'!C14>0,D21/'STR Deal Analyzer'!C14,0) | E38: =IF('STR Deal Analyzer'!C14>0,E21/'STR Deal Analyzer'!C14,0) | F38: =IF('STR Deal Analyzer'!C14>0,F21/'STR Deal Analyzer'!C14,0) | G38: =IF('STR Deal Analyzer'!C14>0,G21/'STR Deal Analyzer'!C14,0) | H38: =IF('STR Deal Analyzer'!C14>0,H21/'STR Deal Analyzer'!C14,0) | I38: =IF('STR Deal Analyzer'!C14>0,I21/'STR Deal Analyzer'!C14,0) | J38: =IF('STR Deal Analyzer'!C14>0,J21/'STR Deal Analyzer'!C14,0) | K38: =IF('STR Deal Analyzer'!C14>0,K21/'STR Deal Analyzer'!C14,0) | L38: =IF('STR Deal Analyzer'!C14>0,L21/'STR Deal Analyzer'!C14,0)
B39: Cash on Cash Return | C39: =IF('STR Deal Analyzer'!C33>0,C23/'STR Deal Analyzer'!C33,0) | D39: =IF('STR Deal Analyzer'!C33>0,D23/'STR Deal Analyzer'!C33,0) | E39: =IF('STR Deal Analyzer'!C33>0,E23/'STR Deal Analyzer'!C33,0) | F39: =IF('STR Deal Analyzer'!C33>0,F23/'STR Deal Analyzer'!C33,0) | G39: =IF('STR Deal Analyzer'!C33>0,G23/'STR Deal Analyzer'!C33,0) | H39: =IF('STR Deal Analyzer'!C33>0,H23/'STR Deal Analyzer'!C33,0) | I39: =IF('STR Deal Analyzer'!C33>0,I23/'STR Deal Analyzer'!C33,0) | J39: =IF('STR Deal Analyzer'!C33>0,J23/'STR Deal Analyzer'!C33,0) | K39: =IF('STR Deal Analyzer'!C33>0,K23/'STR Deal Analyzer'!C33,0) | L39: =IF('STR Deal Analyzer'!C33>0,L23/'STR Deal Analyzer'!C33,0)
B40: Return on Equity | C40: =IF(C32>0,C23/C32,0) | D40: =IF(D32>0,D23/D32,0) | E40: =IF(E32>0,E23/E32,0) | F40: =IF(F32>0,F23/F32,0) | G40: =IF(G32>0,G23/G32,0) | H40: =IF(H32>0,H23/H32,0) | I40: =IF(I32>0,I23/I32,0) | J40: =IF(J32>0,J23/J32,0) | ... L40: =IF(L32>0,L23/L32,0)

Sheet Sensitivity Analysis
B1: COC SENSITIVITY — ADR vs OCCUPANCY
B3: Base ADR: | C3: ='STR Deal Analyzer'!C36
B4: Base Occ: | C4: ='STR Deal Analyzer'!F36
B5: Total Cash In: | C5: ='STR Deal Analyzer'!C33
B7: COC % | C7: 50% Occ | D7: 55% Occ | E7: 60% Occ | F7: 65% Occ | G7: 70% Occ | H7: 75% Occ | I7: 80% Occ
B8: ADR $-75 | C8: =IF(C5>0,(((((C3-75)*'STR Deal Analyzer'!C37*0.5+'STR Deal Analyzer'!C48*'STR Deal Analyzer'!F48*12*0.5/'STR Deal Analyzer'!F36)-((C3-75)*'STR Deal Analyzer'!C37*0.5+'STR Deal Analyzer'!C48*'STR Deal Analyzer'!F48*12*0.5/'STR Deal Analyzer'!F36)*'STR Deal Analyzer'!C45-'STR Deal Analyzer'!C48*'STR Deal Analyzer'!F48*12*0.5/'STR Deal Analyzer'!F36)-(((C3-75)*'STR Deal Analyzer'!C37*0.5+'STR Deal Analyzer'!C48*'STR Deal Analyzer'!F48*12*0.5/'STR Deal Analyzer'!F36)-((C3-75)*'STR Deal Analyzer'!C37*0.5+'STR Deal Analyzer'!C48*'STR Deal Analyzer'!F48*12*0.5/'STR Deal Analyzer'!F36)*'STR Deal Analyzer'!C45-'STR Deal Analyzer'!C48*'STR Deal Analyzer'!F48*12*0.5/'STR Deal Analyzer'!F36)*'STR Deal Analyzer'!C56)-'STR Deal Analyzer'!C60-'STR Deal Analyzer'!F60-'STR Deal Analyzer'!C61-'STR Deal Analyzer'!C72-'STR Deal Analyzer'!F61)/C5,0) | D8: =IF(C5>0,(((((C3-75)*'STR Deal Analyzer'!C37*0.55+'STR Deal Analyzer'!C48*'STR Deal Analyzer'!F48*12*0.55/'STR Deal Analyzer'!F36)-((C3-75)*'STR Deal Analyzer'!C37*0.55+'STR Deal Analyzer'!C48*'STR Deal Analyzer'!F48*12*0.55/'STR Deal Analyzer'!F36)*'STR Deal Analyzer'!C45-'STR Deal Analyzer'!C48*'STR Deal Analyzer'!F48*12*0.55/'STR Deal Analyzer'!F36)-(((C3-75)*'STR Deal Analyzer'!C37*0.55+'STR Deal Analyzer'!C48*'STR Deal Analyzer'!F48*12*0.55/'STR Deal Analyzer'!F36)-((C3-75)*'STR Deal Analyzer'!C37*0.55+'STR Deal Analyzer'!C48*'STR Deal Analyzer'!F48*12*0.55/'STR Deal Analyzer'!F36)*'STR Deal Analyzer'!C45-'STR Deal Analyzer'!C48*'STR Deal Analyzer'!F48*12*0.55/'STR Deal Analyzer'!F36)*'STR Deal Analyzer'!C56)-'STR Deal Analyzer'!C60-'STR Deal Analyzer'!F60-'STR Deal Analyzer'!C61-'STR Deal Analyzer'!C72-'STR Deal Analyzer'!F61)/C5,0) | E8: =IF(C5>0,(((((C3-75)*'STR Deal Analyzer'!C37*0.6+'STR Deal Analyzer'!C48*'STR Deal Analyzer'!F48*12*0.6/'STR Deal Analyzer'!F36)-((C3-75)*'STR Deal Analyzer'!C37*0.6+'STR Deal Analyzer'!C48*'STR Deal Analyzer'!F48*12*0.6/'STR Deal Analyzer'!F36)*'STR Deal Analyzer'!C45-'STR Deal Analyzer'!C48*'STR Deal Analyzer'!F48*12*0.6/'STR Deal Analyzer'!F36)-(((C3-75)*'STR Deal Analyzer'!C37*0.6+'STR Deal Analyzer'!C48*'STR Deal Analyzer'!F48*12*0.6/'STR Deal Analyzer'!F36)-((C3-75)*'STR Deal Analyzer'!C37*0.6+'STR Deal Analyzer'!C48*'STR Deal Analyzer'!F48*12*0.6/'STR Deal Analyzer'!F36)*'STR Deal Analyzer'!C45-'STR Deal Analyzer'!C48*'STR Deal Analyzer'!F48*12*0.6/'STR Deal Analyzer'!F36)*'STR Deal Analyzer'!C56)-'STR Deal Analyzer'!C60-'STR Deal Analyzer'!F60-'STR Deal Analyzer'!C61-'STR Deal Analyzer'!C72-'STR Deal Analyzer'!F61)/C5,0) | F8: =IF(C5>0,(((((C3-75)*'STR Deal Analyzer'!C37*0.65+'STR Deal Analyzer'!C48*'STR Deal Analyzer'!F48*12*0.65/'STR Deal Analyzer'!F36)-((C3-75)*'STR Deal Analyzer'!C37*0.65+'STR Deal Analyzer'!C48*'STR Deal Analyzer'!F48*12*0.65/'STR Deal Analyzer'!F36)*'STR Deal Analyzer'!C45-'STR Deal Analyzer'!C48*'STR Deal Analyzer'!F48*12*0.65/'STR Deal Analyzer'!F36)-(((C3-75)*'STR Deal Analyzer'!C37*0.65+'STR Deal Analyzer'!C48*'STR Deal Analyzer'!F48*12*0.65/'STR Deal Analyzer'!F36)-((C3-75)*'STR Deal Analyzer'!C37*0.65+'STR Deal Analyzer'!C48*'STR Deal Analyzer'!F48*12*0.65/'STR Deal Analyzer'!F36)*'STR Deal Analyzer'!C45-'STR Deal Analyzer'!C48*'STR Deal Analyzer'!F48*12*0.65/'STR Deal Analyzer'!F36)*'STR Deal Analyzer'!C56)-'STR Deal Analyzer'!C60-'STR Deal Analyzer'!F60-'STR Deal Analyzer'!C61-'STR Deal Analyzer'!C72-'STR Deal Analyzer'!F61)/C5,0) | G8: =IF(C5>0,(((((C3-75)*'STR Deal Analyzer'!C37*0.7+'STR Deal Analyzer'!C48*'STR Deal Analyzer'!F48*12*0.7/'STR Deal Analyzer'!F36)-((C3-75)*'STR Deal Analyzer'!C37*0.7+'STR Deal Analyzer'!C48*'STR Deal Analyzer'!F48*12*0.7/'STR Deal Analyzer'!F36)*'STR Deal Analyzer'!C45-'STR Deal Analyzer'!C48*'STR Deal Analyzer'!F48*12*0.7/'STR Deal Analyzer'!F36)-(((C3-75)*'STR Deal Analyzer'!C37*0.7+'STR Deal Analyzer'!C48*'STR Deal Analyzer'!F48*12*0.7/'STR Deal Analyzer'!F36)-((C3-75)*'STR Deal Analyzer'!C37*0.7+'STR Deal Analyzer'!C48*'STR Deal Analyzer'!F48*12*0.7/'STR Deal Analyzer'!F36)*'STR Deal Analyzer'!C45-'STR Deal Analyzer'!C48*'STR Deal Analyzer'!F48*12*0.7/'STR Deal Analyzer'!F36)*'STR Deal Analyzer'!C56)-'STR Deal Analyzer'!C60-'STR Deal Analyzer'!F60-'STR Deal Analyzer'!C61-'STR Deal Analyzer'!C72-'STR Deal Analyzer'!F61)/C5,0) | H8: =IF(C5>0,(((((C3-75)*'STR Deal Analyzer'!C37*0.75+'STR Deal Analyzer'!C48*'STR Deal Analyzer'!F48*12*0.75/'STR Deal Analyzer'!F36)-((C3-75)*'STR Deal Analyzer'!C37*0.75+'STR Deal Analyzer'!C48*'STR Deal Analyzer'!F48*12*0.75/'STR Deal Analyzer'!F36)*'STR Deal Analyzer'!C45-'STR Deal Analyzer'!C48*'STR Deal Analyzer'!F48*12*0.75/'STR Deal Analyzer'!F36)-(((C3-75)*'STR Deal Analyzer'!C37*0.75+'STR Deal Analyzer'!C48*'STR Deal Analyzer'!F48*12*0.75/'STR Deal Analyzer'!F36)-((C3-75)*'STR Deal Analyzer'!C37*0.75+'STR Deal Analyzer'!C48*'STR Deal Analyzer'!F48*12*0.75/'STR Deal Analyzer'!F36)*'STR Deal Analyzer'!C45-'STR Deal Analyzer'!C48*'STR Deal Analyzer'!F48*12*0.75/'STR Deal Analyzer'!F36)*'STR Deal Analyzer'!C56)-'STR Deal Analyzer'!C60-'STR Deal Analyzer'!F60-'STR Deal Analyzer'!C61-'STR Deal Analyzer'!C72-'STR Deal Analyzer'!F61)/C5,0) | I8: =IF(C5>0,(((((C3-75)*'STR Deal Analyzer'!C37*0.8+'STR Deal Analyzer'!C48*'STR Deal Analyzer'!F48*12*0.8/'STR Deal Analyzer'!F36)-((C3-75)*'STR Deal Analyzer'!C37*0.8+'STR Deal Analyzer'!C48*'STR Deal Analyzer'!F48*12*0.8/'STR Deal Analyzer'!F36)*'STR Deal Analyzer'!C45-'STR Deal Analyzer'!C48*'STR Deal Analyzer'!F48*12*0.8/'STR Deal Analyzer'!F36)-(((C3-75)*'STR Deal Analyzer'!C37*0.8+'STR Deal Analyzer'!C48*'STR Deal Analyzer'!F48*12*0.8/'STR Deal Analyzer'!F36)-((C3-75)*'STR Deal Analyzer'!C37*0.8+'STR Deal Analyzer'!C48*'STR Deal Analyzer'!F48*12*0.8/'STR Deal Analyzer'!F36)*'STR Deal Analyzer'!C45-'STR Deal Analyzer'!C48*'STR Deal Analyzer'!F48*12*0.8/'STR Deal Analyzer'!F36)*'STR Deal Analyzer'!C56)-'STR Deal Analyzer'!C60-'STR Deal Analyzer'!F60-'STR Deal Analyzer'!C61-'STR Deal Analyzer'!C72-'STR Deal Analyzer'!F61)/C5,0)
B9: ADR $-50 | C9: =IF(C5>0,(((((C3-50)*'STR Deal Analyzer'!C37*0.5+'STR Deal Analyzer'!C48*'STR Deal Analyzer'!F48*12*0.5/'STR Deal Analyzer'!F36)-((C3-50)*'STR Deal Analyzer'!C37*0.5+'STR Deal Analyzer'!C48*'STR Deal Analyzer'!F48*12*0.5/'STR Deal Analyzer'!F36)*'STR Deal Analyzer'!C45-'STR Deal Analyzer'!C48*'STR Deal Analyzer'!F48*12*0.5/'STR Deal Analyzer'!F36)-(((C3-50)*'STR Deal Analyzer'!C37*0.5+'STR Deal Analyzer'!C48*'STR Deal Analyzer'!F48*12*0.5/'STR Deal Analyzer'!F36)-((C3-50)*'STR Deal Analyzer'!C37*0.5+'STR Deal Analyzer'!C48*'STR Deal Analyzer'!F48*12*0.5/'STR Deal Analyzer'!F36)*'STR Deal Analyzer'!C45-'STR Deal Analyzer'!C48*'STR Deal Analyzer'!F48*12*0.5/'STR Deal Analyzer'!F36)*'STR Deal Analyzer'!C56)-'STR Deal Analyzer'!C60-'STR Deal Analyzer'!F60-'STR Deal Analyzer'!C61-'STR Deal Analyzer'!C72-'STR Deal Analyzer'!F61)/C5,0) | D9: =IF(C5>0,(((((C3-50)*'STR Deal Analyzer'!C37*0.55+'STR Deal Analyzer'!C48*'STR Deal Analyzer'!F48*12*0.55/'STR Deal Analyzer'!F36)-((C3-50)*'STR Deal Analyzer'!C37*0.55+'STR Deal Analyzer'!C48*'STR Deal Analyzer'!F48*12*0.55/'STR Deal Analyzer'!F36)*'STR Deal Analyzer'!C45-'STR Deal Analyzer'!C48*'STR Deal Analyzer'!F48*12*0.55/'STR Deal Analyzer'!F36)-(((C3-50)*'STR Deal Analyzer'!C37*0.55+'STR Deal Analyzer'!C48*'STR Deal Analyzer'!F48*12*0.55/'STR Deal Analyzer'!F36)-((C3-50)*'STR Deal Analyzer'!C37*0.55+'STR Deal Analyzer'!C48*'STR Deal Analyzer'!F48*12*0.55/'STR Deal Analyzer'!F36)*'STR Deal Analyzer'!C45-'STR Deal Analyzer'!C48*'STR Deal Analyzer'!F48*12*0.55/'STR Deal Analyzer'!F36)*'STR Deal Analyzer'!C56)-'STR Deal Analyzer'!C60-'STR Deal Analyzer'!F60-'STR Deal Analyzer'!C61-'STR Deal Analyzer'!C72-'STR Deal Analyzer'!F61)/C5,0) | E9: =IF(C5>0,(((((C3-50)*'STR Deal Analyzer'!C37*0.6+'STR Deal Analyzer'!C48*'STR Deal Analyzer'!F48*12*0.6/'STR Deal Analyzer'!F36)-((C3-50)*'STR Deal Analyzer'!C37*0.6+'STR Deal Analyzer'!C48*'STR Deal Analyzer'!F48*12*0.6/'STR Deal Analyzer'!F36)*'STR Deal Analyzer'!C45-'STR Deal Analyzer'!C48*'STR Deal Analyzer'!F48*12*0.6/'STR Deal Analyzer'!F36)-(((C3-50)*'STR Deal Analyzer'!C37*0.6+'STR Deal Analyzer'!C48*'STR Deal Analyzer'!F48*12*0.6/'STR Deal Analyzer'!F36)-((C3-50)*'STR Deal Analyzer'!C37*0.6+'STR Deal Analyzer'!C48*'STR Deal Analyzer'!F48*12*0.6/'STR Deal Analyzer'!F36)*'STR Deal Analyzer'!C45-'STR Deal Analyzer'!C48*'STR Deal Analyzer'!F48*12*0.6/'STR Deal Analyzer'!F36)*'STR Deal Analyzer'!C56)-'STR Deal Analyzer'!C60-'STR Deal Analyzer'!F60-'STR Deal Analyzer'!C61-'STR Deal Analyzer'!C72-'STR Deal Analyzer'!F61)/C5,0) | F9: =IF(C5>0,(((((C3-50)*'STR Deal Analyzer'!C37*0.65+'STR Deal Analyzer'!C48*'STR Deal Analyzer'!F48*12*0.65/'STR Deal Analyzer'!F36)-((C3-50)*'STR Deal Analyzer'!C37*0.65+'STR Deal Analyzer'!C48*'STR Deal Analyzer'!F48*12*0.65/'STR Deal Analyzer'!F36)*'STR Deal Analyzer'!C45-'STR Deal Analyzer'!C48*'STR Deal Analyzer'!F48*12*0.65/'STR Deal Analyzer'!F36)-(((C3-50)*'STR Deal Analyzer'!C37*0.65+'STR Deal Analyzer'!C48*'STR Deal Analyzer'!F48*12*0.65/'STR Deal Analyzer'!F36)-((C3-50)*'STR Deal Analyzer'!C37*0.65+'STR Deal Analyzer'!C48*'STR Deal Analyzer'!F48*12*0.65/'STR Deal Analyzer'!F36)*'STR Deal Analyzer'!C45-'STR Deal Analyzer'!C48*'STR Deal Analyzer'!F48*12*0.65/'STR Deal Analyzer'!F36)*'STR Deal Analyzer'!C56)-'STR Deal Analyzer'!C60-'STR Deal Analyzer'!F60-'STR Deal Analyzer'!C61-'STR Deal Analyzer'!C72-'STR Deal Analyzer'!F61)/C5,0) | G9: =IF(C5>0,(((((C3-50)*'STR Deal Analyzer'!C37*0.7+'STR Deal Analyzer'!C48*'STR Deal Analyzer'!F48*12*0.7/'STR Deal Analyzer'!F36)-((C3-50)*'STR Deal Analyzer'!C37*0.7+'STR Deal Analyzer'!C48*'STR Deal Analyzer'!F48*12*0.7/'STR Deal Analyzer'!F36)*'STR Deal Analyzer'!C45-'STR Deal Analyzer'!C48*'STR Deal Analyzer'!F48*12*0.7/'STR Deal Analyzer'!F36)-(((C3-50)*'STR Deal Analyzer'!C37*0.7+'STR Deal Analyzer'!C48*'STR Deal Analyzer'!F48*12*0.7/'STR Deal Analyzer'!F36)-((C3-50)*'STR Deal Analyzer'!C37*0.7+'STR Deal Analyzer'!C48*'STR Deal Analyzer'!F48*12*0.7/'STR Deal Analyzer'!F36)*'STR Deal Analyzer'!C45-'STR Deal Analyzer'!C48*'STR Deal Analyzer'!F48*12*0.7/'STR Deal Analyzer'!F36)*'STR Deal Analyzer'!C56)-'STR Deal Analyzer'!C60-'STR Deal Analyzer'!F60-'STR Deal Analyzer'!C61-'STR Deal Analyzer'!C72-'STR Deal Analyzer'!F61)/C5,0) | H9: =IF(C5>0,(((((C3-50)*'STR Deal Analyzer'!C37*0.75+'STR Deal Analyzer'!C48*'STR Deal Analyzer'!F48*12*0.75/'STR Deal Analyzer'!F36)-((C3-50)*'STR Deal Analyzer'!C37*0.75+'STR Deal Analyzer'!C48*'STR Deal Analyzer'!F48*12*0.75/'STR Deal Analyzer'!F36)*'STR Deal Analyzer'!C45-'STR Deal Analyzer'!C48*'STR Deal Analyzer'!F48*12*0.75/'STR Deal Analyzer'!F36)-(((C3-50)*'STR Deal Analyzer'!C37*0.75+'STR Deal Analyzer'!C48*'STR Deal Analyzer'!F48*12*0.75/'STR Deal Analyzer'!F36)-((C3-50)*'STR Deal Analyzer'!C37*0.75+'STR Deal Analyzer'!C48*'STR Deal Analyzer'!F48*12*0.75/'STR Deal Analyzer'!F36)*'STR Deal Analyzer'!C45-'STR Deal Analyzer'!C48*'STR Deal Analyzer'!F48*12*0.75/'STR Deal Analyzer'!F36)*'STR Deal Analyzer'!C56)-'STR Deal Analyzer'!C60-'STR Deal Analyzer'!F60-'STR Deal Analyzer'!C61-'STR Deal Analyzer'!C72-'STR Deal Analyzer'!F61)/C5,0) | I9: =IF(C5>0,(((((C3-50)*'STR Deal Analyzer'!C37*0.8+'STR Deal Analyzer'!C48*'STR Deal Analyzer'!F48*12*0.8/'STR Deal Analyzer'!F36)-((C3-50)*'STR Deal Analyzer'!C37*0.8+'STR Deal Analyzer'!C48*'STR Deal Analyzer'!F48*12*0.8/'STR Deal Analyzer'!F36)*'STR Deal Analyzer'!C45-'STR Deal Analyzer'!C48*'STR Deal Analyzer'!F48*12*0.8/'STR Deal Analyzer'!F36)-(((C3-50)*'STR Deal Analyzer'!C37*0.8+'STR Deal Analyzer'!C48*'STR Deal Analyzer'!F48*12*0.8/'STR Deal Analyzer'!F36)-((C3-50)*'STR Deal Analyzer'!C37*0.8+'STR Deal Analyzer'!C48*'STR Deal Analyzer'!F48*12*0.8/'STR Deal Analyzer'!F36)*'STR Deal Analyzer'!C45-'STR Deal Analyzer'!C48*'STR Deal Analyzer'!F48*12*0.8/'STR Deal Analyzer'!F36)*'STR Deal Analyzer'!C56)-'STR Deal Analyzer'!C60-'STR Deal Analyzer'!F60-'STR Deal Analyzer'!C61-'STR Deal Analyzer'!C72-'STR Deal Analyzer'!F61)/C5,0)
B10: ADR $-25 | C10: =IF(C5>0,(((((C3-25)*'STR Deal Analyzer'!C37*0.5+'STR Deal Analyzer'!C48*'STR Deal Analyzer'!F48*12*0.5/'STR Deal Analyzer'!F36)-((C3-25)*'STR Deal Analyzer'!C37*0.5+'STR Deal Analyzer'!C48*'STR Deal Analyzer'!F48*12*0.5/'STR Deal Analyzer'!F36)*'STR Deal Analyzer'!C45-'STR Deal Analyzer'!C48*'STR Deal Analyzer'!F48*12*0.5/'STR Deal Analyzer'!F36)-(((C3-25)*'STR Deal Analyzer'!C37*0.5+'STR Deal Analyzer'!C48*'STR Deal Analyzer'!F48*12*0.5/'STR Deal Analyzer'!F36)-((C3-25)*'STR Deal Analyzer'!C37*0.5+'STR Deal Analyzer'!C48*'STR Deal Analyzer'!F48*12*0.5/'STR Deal Analyzer'!F36)*'STR Deal Analyzer'!C45-'STR Deal Analyzer'!C48*'STR Deal Analyzer'!F48*12*0.5/'STR Deal Analyzer'!F36)*'STR Deal Analyzer'!C56)-'STR Deal Analyzer'!C60-'STR Deal Analyzer'!F60-'STR Deal Analyzer'!C61-'STR Deal Analyzer'!C72-'STR Deal Analyzer'!F61)/C5,0) | D10: =IF(C5>0,(((((C3-25)*'STR Deal Analyzer'!C37*0.55+'STR Deal Analyzer'!C48*'STR Deal Analyzer'!F48*12*0.55/'STR Deal Analyzer'!F36)-((C3-25)*'STR Deal Analyzer'!C37*0.55+'STR Deal Analyzer'!C48*'STR Deal Analyzer'!F48*12*0.55/'STR Deal Analyzer'!F36)*'STR Deal Analyzer'!C45-'STR Deal Analyzer'!C48*'STR Deal Analyzer'!F48*12*0.55/'STR Deal Analyzer'!F36)-(((C3-25)*'STR Deal Analyzer'!C37*0.55+'STR Deal Analyzer'!C48*'STR Deal Analyzer'!F48*12*0.55/'STR Deal Analyzer'!F36)-((C3-25)*'STR Deal Analyzer'!C37*0.55+'STR Deal Analyzer'!C48*'STR Deal Analyzer'!F48*12*0.55/'STR Deal Analyzer'!F36)*'STR Deal Analyzer'!C45-'STR Deal Analyzer'!C48*'STR Deal Analyzer'!F48*12*0.55/'STR Deal Analyzer'!F36)*'STR Deal Analyzer'!C56)-'STR Deal Analyzer'!C60-'STR Deal Analyzer'!F60-'STR Deal Analyzer'!C61-'STR Deal Analyzer'!C72-'STR Deal Analyzer'!F61)/C5,0) | E10: =IF(C5>0,(((((C3-25)*'STR Deal Analyzer'!C37*0.6+'STR Deal Analyzer'!C48*'STR Deal Analyzer'!F48*12*0.6/'STR Deal Analyzer'!F36)-((C3-25)*'STR Deal Analyzer'!C37*0.6+'STR Deal Analyzer'!C48*'STR Deal Analyzer'!F48*12*0.6/'STR Deal Analyzer'!F36)*'STR Deal Analyzer'!C45-'STR Deal Analyzer'!C48*'STR Deal Analyzer'!F48*12*0.6/'STR Deal Analyzer'!F36)-(((C3-25)*'STR Deal Analyzer'!C37*0.6+'STR Deal Analyzer'!C48*'STR Deal Analyzer'!F48*12*0.6/'STR Deal Analyzer'!F36)-((C3-25)*'STR Deal Analyzer'!C37*0.6+'STR Deal Analyzer'!C48*'STR Deal Analyzer'!F48*12*0.6/'STR Deal Analyzer'!F36)*'STR Deal Analyzer'!C45-'STR Deal Analyzer'!C48*'STR Deal Analyzer'!F48*12*0.6/'STR Deal Analyzer'!F36)*'STR Deal Analyzer'!C56)-'STR Deal Analyzer'!C60-'STR Deal Analyzer'!F60-'STR Deal Analyzer'!C61-'STR Deal Analyzer'!C72-'STR Deal Analyzer'!F61)/C5,0) | F10: =IF(C5>0,(((((C3-25)*'STR Deal Analyzer'!C37*0.65+'STR Deal Analyzer'!C48*'STR Deal Analyzer'!F48*12*0.65/'STR Deal Analyzer'!F36)-((C3-25)*'STR Deal Analyzer'!C37*0.65+'STR Deal Analyzer'!C48*'STR Deal Analyzer'!F48*12*0.65/'STR Deal Analyzer'!F36)*'STR Deal Analyzer'!C45-'STR Deal Analyzer'!C48*'STR Deal Analyzer'!F48*12*0.65/'STR Deal Analyzer'!F36)-(((C3-25)*'STR Deal Analyzer'!C37*0.65+'STR Deal Analyzer'!C48*'STR Deal Analyzer'!F48*12*0.65/'STR Deal Analyzer'!F36)-((C3-25)*'STR Deal Analyzer'!C37*0.65+'STR Deal Analyzer'!C48*'STR Deal Analyzer'!F48*12*0.65/'STR Deal Analyzer'!F36)*'STR Deal Analyzer'!C45-'STR Deal Analyzer'!C48*'STR Deal Analyzer'!F48*12*0.65/'STR Deal Analyzer'!F36)*'STR Deal Analyzer'!C56)-'STR Deal Analyzer'!C60-'STR Deal Analyzer'!F60-'STR Deal Analyzer'!C61-'STR Deal Analyzer'!C72-'STR Deal Analyzer'!F61)/C5,0) | G10: =IF(C5>0,(((((C3-25)*'STR Deal Analyzer'!C37*0.7+'STR Deal Analyzer'!C48*'STR Deal Analyzer'!F48*12*0.7/'STR Deal Analyzer'!F36)-((C3-25)*'STR Deal Analyzer'!C37*0.7+'STR Deal Analyzer'!C48*'STR Deal Analyzer'!F48*12*0.7/'STR Deal Analyzer'!F36)*'STR Deal Analyzer'!C45-'STR Deal Analyzer'!C48*'STR Deal Analyzer'!F48*12*0.7/'STR Deal Analyzer'!F36)-(((C3-25)*'STR Deal Analyzer'!C37*0.7+'STR Deal Analyzer'!C48*'STR Deal Analyzer'!F48*12*0.7/'STR Deal Analyzer'!F36)-((C3-25)*'STR Deal Analyzer'!C37*0.7+'STR Deal Analyzer'!C48*'STR Deal Analyzer'!F48*12*0.7/'STR Deal Analyzer'!F36)*'STR Deal Analyzer'!C45-'STR Deal Analyzer'!C48*'STR Deal Analyzer'!F48*12*0.7/'STR Deal Analyzer'!F36)*'STR Deal Analyzer'!C56)-'STR Deal Analyzer'!C60-'STR Deal Analyzer'!F60-'STR Deal Analyzer'!C61-'STR Deal Analyzer'!C72-'STR Deal Analyzer'!F61)/C5,0) | H10: =IF(C5>0,(((((C3-25)*'STR Deal Analyzer'!C37*0.75+'STR Deal Analyzer'!C48*'STR Deal Analyzer'!F48*12*0.75/'STR Deal Analyzer'!F36)-((C3-25)*'STR Deal Analyzer'!C37*0.75+'STR Deal Analyzer'!C48*'STR Deal Analyzer'!F48*12*0.75/'STR Deal Analyzer'!F36)*'STR Deal Analyzer'!C45-'STR Deal Analyzer'!C48*'STR Deal Analyzer'!F48*12*0.75/'STR Deal Analyzer'!F36)-(((C3-25)*'STR Deal Analyzer'!C37*0.75+'STR Deal Analyzer'!C48*'STR Deal Analyzer'!F48*12*0.75/'STR Deal Analyzer'!F36)-((C3-25)*'STR Deal Analyzer'!C37*0.75+'STR Deal Analyzer'!C48*'STR Deal Analyzer'!F48*12*0.75/'STR Deal Analyzer'!F36)*'STR Deal Analyzer'!C45-'STR Deal Analyzer'!C48*'STR Deal Analyzer'!F48*12*0.75/'STR Deal Analyzer'!F36)*'STR Deal Analyzer'!C56)-'STR Deal Analyzer'!C60-'STR Deal Analyzer'!F60-'STR Deal Analyzer'!C61-'STR Deal Analyzer'!C72-'STR Deal Analyzer'!F61)/C5,0) | I10: =IF(C5>0,(((((C3-25)*'STR Deal Analyzer'!C37*0.8+'STR Deal Analyzer'!C48*'STR Deal Analyzer'!F48*12*0.8/'STR Deal Analyzer'!F36)-((C3-25)*'STR Deal Analyzer'!C37*0.8+'STR Deal Analyzer'!C48*'STR Deal Analyzer'!F48*12*0.8/'STR Deal Analyzer'!F36)*'STR Deal Analyzer'!C45-'STR Deal Analyzer'!C48*'STR Deal Analyzer'!F48*12*0.8/'STR Deal Analyzer'!F36)-(((C3-25)*'STR Deal Analyzer'!C37*0.8+'STR Deal Analyzer'!C48*'STR Deal Analyzer'!F48*12*0.8/'STR Deal Analyzer'!F36)-((C3-25)*'STR Deal Analyzer'!C37*0.8+'STR Deal Analyzer'!C48*'STR Deal Analyzer'!F48*12*0.8/'STR Deal Analyzer'!F36)*'STR Deal Analyzer'!C45-'STR Deal Analyzer'!C48*'STR Deal Analyzer'!F48*12*0.8/'STR Deal Analyzer'!F36)*'STR Deal Analyzer'!C56)-'STR Deal Analyzer'!C60-'STR Deal Analyzer'!F60-'STR Deal Analyzer'!C61-'STR Deal Analyzer'!C72-'STR Deal Analyzer'!F61)/C5,0)
B11: Base ADR | C11: =IF(C5>0,(((((C3+0)*'STR Deal Analyzer'!C37*0.5+'STR Deal Analyzer'!C48*'STR Deal Analyzer'!F48*12*0.5/'STR Deal Analyzer'!F36)-((C3+0)*'STR Deal Analyzer'!C37*0.5+'STR Deal Analyzer'!C48*'STR Deal Analyzer'!F48*12*0.5/'STR Deal Analyzer'!F36)*'STR Deal Analyzer'!C45-'STR Deal Analyzer'!C48*'STR Deal Analyzer'!F48*12*0.5/'STR Deal Analyzer'!F36)-(((C3+0)*'STR Deal Analyzer'!C37*0.5+'STR Deal Analyzer'!C48*'STR Deal Analyzer'!F48*12*0.5/'STR Deal Analyzer'!F36)-((C3+0)*'STR Deal Analyzer'!C37*0.5+'STR Deal Analyzer'!C48*'STR Deal Analyzer'!F48*12*0.5/'STR Deal Analyzer'!F36)*'STR Deal Analyzer'!C45-'STR Deal Analyzer'!C48*'STR Deal Analyzer'!F48*12*0.5/'STR Deal Analyzer'!F36)*'STR Deal Analyzer'!C56)-'STR Deal Analyzer'!C60-'STR Deal Analyzer'!F60-'STR Deal Analyzer'!C61-'STR Deal Analyzer'!C72-'STR Deal Analyzer'!F61)/C5,0) | D11: =IF(C5>0,(((((C3+0)*'STR Deal Analyzer'!C37*0.55+'STR Deal Analyzer'!C48*'STR Deal Analyzer'!F48*12*0.55/'STR Deal Analyzer'!F36)-((C3+0)*'STR Deal Analyzer'!C37*0.55+'STR Deal Analyzer'!C48*'STR Deal Analyzer'!F48*12*0.55/'STR Deal Analyzer'!F36)*'STR Deal Analyzer'!C45-'STR Deal Analyzer'!C48*'STR Deal Analyzer'!F48*12*0.55/'STR Deal Analyzer'!F36)-(((C3+0)*'STR Deal Analyzer'!C37*0.55+'STR Deal Analyzer'!C48*'STR Deal Analyzer'!F48*12*0.55/'STR Deal Analyzer'!F36)-((C3+0)*'STR Deal Analyzer'!C37*0.55+'STR Deal Analyzer'!C48*'STR Deal Analyzer'!F48*12*0.55/'STR Deal Analyzer'!F36)*'STR Deal Analyzer'!C45-'STR Deal Analyzer'!C48*'STR Deal Analyzer'!F48*12*0.55/'STR Deal Analyzer'!F36)*'STR Deal Analyzer'!C56)-'STR Deal Analyzer'!C60-'STR Deal Analyzer'!F60-'STR Deal Analyzer'!C61-'STR Deal Analyzer'!C72-'STR Deal Analyzer'!F61)/C5,0) | E11: =IF(C5>0,(((((C3+0)*'STR Deal Analyzer'!C37*0.6+'STR Deal Analyzer'!C48*'STR Deal Analyzer'!F48*12*0.6/'STR Deal Analyzer'!F36)-((C3+0)*'STR Deal Analyzer'!C37*0.6+'STR Deal Analyzer'!C48*'STR Deal Analyzer'!F48*12*0.6/'STR Deal Analyzer'!F36)*'STR Deal Analyzer'!C45-'STR Deal Analyzer'!C48*'STR Deal Analyzer'!F48*12*0.6/'STR Deal Analyzer'!F36)-(((C3+0)*'STR Deal Analyzer'!C37*0.6+'STR Deal Analyzer'!C48*'STR Deal Analyzer'!F48*12*0.6/'STR Deal Analyzer'!F36)-((C3+0)*'STR Deal Analyzer'!C37*0.6+'STR Deal Analyzer'!C48*'STR Deal Analyzer'!F48*12*0.6/'STR Deal Analyzer'!F36)*'STR Deal Analyzer'!C45-'STR Deal Analyzer'!C48*'STR Deal Analyzer'!F48*12*0.6/'STR Deal Analyzer'!F36)*'STR Deal Analyzer'!C56)-'STR Deal Analyzer'!C60-'STR Deal Analyzer'!F60-'STR Deal Analyzer'!C61-'STR Deal Analyzer'!C72-'STR Deal Analyzer'!F61)/C5,0) | F11: =IF(C5>0,(((((C3+0)*'STR Deal Analyzer'!C37*0.65+'STR Deal Analyzer'!C48*'STR Deal Analyzer'!F48*12*0.65/'STR Deal Analyzer'!F36)-((C3+0)*'STR Deal Analyzer'!C37*0.65+'STR Deal Analyzer'!C48*'STR Deal Analyzer'!F48*12*0.65/'STR Deal Analyzer'!F36)*'STR Deal Analyzer'!C45-'STR Deal Analyzer'!C48*'STR Deal Analyzer'!F48*12*0.65/'STR Deal Analyzer'!F36)-(((C3+0)*'STR Deal Analyzer'!C37*0.65+'STR Deal Analyzer'!C48*'STR Deal Analyzer'!F48*12*0.65/'STR Deal Analyzer'!F36)-((C3+0)*'STR Deal Analyzer'!C37*0.65+'STR Deal Analyzer'!C48*'STR Deal Analyzer'!F48*12*0.65/'STR Deal Analyzer'!F36)*'STR Deal Analyzer'!C45-'STR Deal Analyzer'!C48*'STR Deal Analyzer'!F48*12*0.65/'STR Deal Analyzer'!F36)*'STR Deal Analyzer'!C56)-'STR Deal Analyzer'!C60-'STR Deal Analyzer'!F60-'STR Deal Analyzer'!C61-'STR Deal Analyzer'!C72-'STR Deal Analyzer'!F61)/C5,0) | G11: =IF(C5>0,(((((C3+0)*'STR Deal Analyzer'!C37*0.7+'STR Deal Analyzer'!C48*'STR Deal Analyzer'!F48*12*0.7/'STR Deal Analyzer'!F36)-((C3+0)*'STR Deal Analyzer'!C37*0.7+'STR Deal Analyzer'!C48*'STR Deal Analyzer'!F48*12*0.7/'STR Deal Analyzer'!F36)*'STR Deal Analyzer'!C45-'STR Deal Analyzer'!C48*'STR Deal Analyzer'!F48*12*0.7/'STR Deal Analyzer'!F36)-(((C3+0)*'STR Deal Analyzer'!C37*0.7+'STR Deal Analyzer'!C48*'STR Deal Analyzer'!F48*12*0.7/'STR Deal Analyzer'!F36)-((C3+0)*'STR Deal Analyzer'!C37*0.7+'STR Deal Analyzer'!C48*'STR Deal Analyzer'!F48*12*0.7/'STR Deal Analyzer'!F36)*'STR Deal Analyzer'!C45-'STR Deal Analyzer'!C48*'STR Deal Analyzer'!F48*12*0.7/'STR Deal Analyzer'!F36)*'STR Deal Analyzer'!C56)-'STR Deal Analyzer'!C60-'STR Deal Analyzer'!F60-'STR Deal Analyzer'!C61-'STR Deal Analyzer'!C72-'STR Deal Analyzer'!F61)/C5,0) | H11: =IF(C5>0,(((((C3+0)*'STR Deal Analyzer'!C37*0.75+'STR Deal Analyzer'!C48*'STR Deal Analyzer'!F48*12*0.75/'STR Deal Analyzer'!F36)-((C3+0)*'STR Deal Analyzer'!C37*0.75+'STR Deal Analyzer'!C48*'STR Deal Analyzer'!F48*12*0.75/'STR Deal Analyzer'!F36)*'STR Deal Analyzer'!C45-'STR Deal Analyzer'!C48*'STR Deal Analyzer'!F48*12*0.75/'STR Deal Analyzer'!F36)-(((C3+0)*'STR Deal Analyzer'!C37*0.75+'STR Deal Analyzer'!C48*'STR Deal Analyzer'!F48*12*0.75/'STR Deal Analyzer'!F36)-((C3+0)*'STR Deal Analyzer'!C37*0.75+'STR Deal Analyzer'!C48*'STR Deal Analyzer'!F48*12*0.75/'STR Deal Analyzer'!F36)*'STR Deal Analyzer'!C45-'STR Deal Analyzer'!C48*'STR Deal Analyzer'!F48*12*0.75/'STR Deal Analyzer'!F36)*'STR Deal Analyzer'!C56)-'STR Deal Analyzer'!C60-'STR Deal Analyzer'!F60-'STR Deal Analyzer'!C61-'STR Deal Analyzer'!C72-'STR Deal Analyzer'!F61)/C5,0) | I11: =IF(C5>0,(((((C3+0)*'STR Deal Analyzer'!C37*0.8+'STR Deal Analyzer'!C48*'STR Deal Analyzer'!F48*12*0.8/'STR Deal Analyzer'!F36)-((C3+0)*'STR Deal Analyzer'!C37*0.8+'STR Deal Analyzer'!C48*'STR Deal Analyzer'!F48*12*0.8/'STR Deal Analyzer'!F36)*'STR Deal Analyzer'!C45-'STR Deal Analyzer'!C48*'STR Deal Analyzer'!F48*12*0.8/'STR Deal Analyzer'!F36)-(((C3+0)*'STR Deal Analyzer'!C37*0.8+'STR Deal Analyzer'!C48*'STR Deal Analyzer'!F48*12*0.8/'STR Deal Analyzer'!F36)-((C3+0)*'STR Deal Analyzer'!C37*0.8+'STR Deal Analyzer'!C48*'STR Deal Analyzer'!F48*12*0.8/'STR Deal Analyzer'!F36)*'STR Deal Analyzer'!C45-'STR Deal Analyzer'!C48*'STR Deal Analyzer'!F48*12*0.8/'STR Deal Analyzer'!F36)*'STR Deal Analyzer'!C56)-'STR Deal Analyzer'!C60-'STR Deal Analyzer'!F60-'STR Deal Analyzer'!C61-'STR Deal Analyzer'!C72-'STR Deal Analyzer'!F61)/C5,0)
B12: ADR +$25 | C12: =IF(C5>0,(((((C3+25)*'STR Deal Analyzer'!C37*0.5+'STR Deal Analyzer'!C48*'STR Deal Analyzer'!F48*12*0.5/'STR Deal Analyzer'!F36)-((C3+25)*'STR Deal Analyzer'!C37*0.5+'STR Deal Analyzer'!C48*'STR Deal Analyzer'!F48*12*0.5/'STR Deal Analyzer'!F36)*'STR Deal Analyzer'!C45-'STR Deal Analyzer'!C48*'STR Deal Analyzer'!F48*12*0.5/'STR Deal Analyzer'!F36)-(((C3+25)*'STR Deal Analyzer'!C37*0.5+'STR Deal Analyzer'!C48*'STR Deal Analyzer'!F48*12*0.5/'STR Deal Analyzer'!F36)-((C3+25)*'STR Deal Analyzer'!C37*0.5+'STR Deal Analyzer'!C48*'STR Deal Analyzer'!F48*12*0.5/'STR Deal Analyzer'!F36)*'STR Deal Analyzer'!C45-'STR Deal Analyzer'!C48*'STR Deal Analyzer'!F48*12*0.5/'STR Deal Analyzer'!F36)*'STR Deal Analyzer'!C56)-'STR Deal Analyzer'!C60-'STR Deal Analyzer'!F60-'STR Deal Analyzer'!C61-'STR Deal Analyzer'!C72-'STR Deal Analyzer'!F61)/C5,0) | D12: =IF(C5>0,(((((C3+25)*'STR Deal Analyzer'!C37*0.55+'STR Deal Analyzer'!C48*'STR Deal Analyzer'!F48*12*0.55/'STR Deal Analyzer'!F36)-((C3+25)*'STR Deal Analyzer'!C37*0.55+'STR Deal Analyzer'!C48*'STR Deal Analyzer'!F48*12*0.55/'STR Deal Analyzer'!F36)*'STR Deal Analyzer'!C45-'STR Deal Analyzer'!C48*'STR Deal Analyzer'!F48*12*0.55/'STR Deal Analyzer'!F36)-(((C3+25)*'STR Deal Analyzer'!C37*0.55+'STR Deal Analyzer'!C48*'STR Deal Analyzer'!F48*12*0.55/'STR Deal Analyzer'!F36)-((C3+25)*'STR Deal Analyzer'!C37*0.55+'STR Deal Analyzer'!C48*'STR Deal Analyzer'!F48*12*0.55/'STR Deal Analyzer'!F36)*'STR Deal Analyzer'!C45-'STR Deal Analyzer'!C48*'STR Deal Analyzer'!F48*12*0.55/'STR Deal Analyzer'!F36)*'STR Deal Analyzer'!C56)-'STR Deal Analyzer'!C60-'STR Deal Analyzer'!F60-'STR Deal Analyzer'!C61-'STR Deal Analyzer'!C72-'STR Deal Analyzer'!F61)/C5,0) | E12: =IF(C5>0,(((((C3+25)*'STR Deal Analyzer'!C37*0.6+'STR Deal Analyzer'!C48*'STR Deal Analyzer'!F48*12*0.6/'STR Deal Analyzer'!F36)-((C3+25)*'STR Deal Analyzer'!C37*0.6+'STR Deal Analyzer'!C48*'STR Deal Analyzer'!F48*12*0.6/'STR Deal Analyzer'!F36)*'STR Deal Analyzer'!C45-'STR Deal Analyzer'!C48*'STR Deal Analyzer'!F48*12*0.6/'STR Deal Analyzer'!F36)-(((C3+25)*'STR Deal Analyzer'!C37*0.6+'STR Deal Analyzer'!C48*'STR Deal Analyzer'!F48*12*0.6/'STR Deal Analyzer'!F36)-((C3+25)*'STR Deal Analyzer'!C37*0.6+'STR Deal Analyzer'!C48*'STR Deal Analyzer'!F48*12*0.6/'STR Deal Analyzer'!F36)*'STR Deal Analyzer'!C45-'STR Deal Analyzer'!C48*'STR Deal Analyzer'!F48*12*0.6/'STR Deal Analyzer'!F36)*'STR Deal Analyzer'!C56)-'STR Deal Analyzer'!C60-'STR Deal Analyzer'!F60-'STR Deal Analyzer'!C61-'STR Deal Analyzer'!C72-'STR Deal Analyzer'!F61)/C5,0) | F12: =IF(C5>0,(((((C3+25)*'STR Deal Analyzer'!C37*0.65+'STR Deal Analyzer'!C48*'STR Deal Analyzer'!F48*12*0.65/'STR Deal Analyzer'!F36)-((C3+25)*'STR Deal Analyzer'!C37*0.65+'STR Deal Analyzer'!C48*'STR Deal Analyzer'!F48*12*0.65/'STR Deal Analyzer'!F36)*'STR Deal Analyzer'!C45-'STR Deal Analyzer'!C48*'STR Deal Analyzer'!F48*12*0.65/'STR Deal Analyzer'!F36)-(((C3+25)*'STR Deal Analyzer'!C37*0.65+'STR Deal Analyzer'!C48*'STR Deal Analyzer'!F48*12*0.65/'STR Deal Analyzer'!F36)-((C3+25)*'STR Deal Analyzer'!C37*0.65+'STR Deal Analyzer'!C48*'STR Deal Analyzer'!F48*12*0.65/'STR Deal Analyzer'!F36)*'STR Deal Analyzer'!C45-'STR Deal Analyzer'!C48*'STR Deal Analyzer'!F48*12*0.65/'STR Deal Analyzer'!F36)*'STR Deal Analyzer'!C56)-'STR Deal Analyzer'!C60-'STR Deal Analyzer'!F60-'STR Deal Analyzer'!C61-'STR Deal Analyzer'!C72-'STR Deal Analyzer'!F61)/C5,0) | G12: =IF(C5>0,(((((C3+25)*'STR Deal Analyzer'!C37*0.7+'STR Deal Analyzer'!C48*'STR Deal Analyzer'!F48*12*0.7/'STR Deal Analyzer'!F36)-((C3+25)*'STR Deal Analyzer'!C37*0.7+'STR Deal Analyzer'!C48*'STR Deal Analyzer'!F48*12*0.7/'STR Deal Analyzer'!F36)*'STR Deal Analyzer'!C45-'STR Deal Analyzer'!C48*'STR Deal Analyzer'!F48*12*0.7/'STR Deal Analyzer'!F36)-(((C3+25)*'STR Deal Analyzer'!C37*0.7+'STR Deal Analyzer'!C48*'STR Deal Analyzer'!F48*12*0.7/'STR Deal Analyzer'!F36)-((C3+25)*'STR Deal Analyzer'!C37*0.7+'STR Deal Analyzer'!C48*'STR Deal Analyzer'!F48*12*0.7/'STR Deal Analyzer'!F36)*'STR Deal Analyzer'!C45-'STR Deal Analyzer'!C48*'STR Deal Analyzer'!F48*12*0.7/'STR Deal Analyzer'!F36)*'STR Deal Analyzer'!C56)-'STR Deal Analyzer'!C60-'STR Deal Analyzer'!F60-'STR Deal Analyzer'!C61-'STR Deal Analyzer'!C72-'STR Deal Analyzer'!F61)/C5,0) | H12: =IF(C5>0,(((((C3+25)*'STR Deal Analyzer'!C37*0.75+'STR Deal Analyzer'!C48*'STR Deal Analyzer'!F48*12*0.75/'STR Deal Analyzer'!F36)-((C3+25)*'STR Deal Analyzer'!C37*0.75+'STR Deal Analyzer'!C48*'STR Deal Analyzer'!F48*12*0.75/'STR Deal Analyzer'!F36)*'STR Deal Analyzer'!C45-'STR Deal Analyzer'!C48*'STR Deal Analyzer'!F48*12*0.75/'STR Deal Analyzer'!F36)-(((C3+25)*'STR Deal Analyzer'!C37*0.75+'STR Deal Analyzer'!C48*'STR Deal Analyzer'!F48*12*0.75/'STR Deal Analyzer'!F36)-((C3+25)*'STR Deal Analyzer'!C37*0.75+'STR Deal Analyzer'!C48*'STR Deal Analyzer'!F48*12*0.75/'STR Deal Analyzer'!F36)*'STR Deal Analyzer'!C45-'STR Deal Analyzer'!C48*'STR Deal Analyzer'!F48*12*0.75/'STR Deal Analyzer'!F36)*'STR Deal Analyzer'!C56)-'STR Deal Analyzer'!C60-'STR Deal Analyzer'!F60-'STR Deal Analyzer'!C61-'STR Deal Analyzer'!C72-'STR Deal Analyzer'!F61)/C5,0) | I12: =IF(C5>0,(((((C3+25)*'STR Deal Analyzer'!C37*0.8+'STR Deal Analyzer'!C48*'STR Deal Analyzer'!F48*12*0.8/'STR Deal Analyzer'!F36)-((C3+25)*'STR Deal Analyzer'!C37*0.8+'STR Deal Analyzer'!C48*'STR Deal Analyzer'!F48*12*0.8/'STR Deal Analyzer'!F36)*'STR Deal Analyzer'!C45-'STR Deal Analyzer'!C48*'STR Deal Analyzer'!F48*12*0.8/'STR Deal Analyzer'!F36)-(((C3+25)*'STR Deal Analyzer'!C37*0.8+'STR Deal Analyzer'!C48*'STR Deal Analyzer'!F48*12*0.8/'STR Deal Analyzer'!F36)-((C3+25)*'STR Deal Analyzer'!C37*0.8+'STR Deal Analyzer'!C48*'STR Deal Analyzer'!F48*12*0.8/'STR Deal Analyzer'!F36)*'STR Deal Analyzer'!C45-'STR Deal Analyzer'!C48*'STR Deal Analyzer'!F48*12*0.8/'STR Deal Analyzer'!F36)*'STR Deal Analyzer'!C56)-'STR Deal Analyzer'!C60-'STR Deal Analyzer'!F60-'STR Deal Analyzer'!C61-'STR Deal Analyzer'!C72-'STR Deal Analyzer'!F61)/C5,0)
B13: ADR +$50 | C13: =IF(C5>0,(((((C3+50)*'STR Deal Analyzer'!C37*0.5+'STR Deal Analyzer'!C48*'STR Deal Analyzer'!F48*12*0.5/'STR Deal Analyzer'!F36)-((C3+50)*'STR Deal Analyzer'!C37*0.5+'STR Deal Analyzer'!C48*'STR Deal Analyzer'!F48*12*0.5/'STR Deal Analyzer'!F36)*'STR Deal Analyzer'!C45-'STR Deal Analyzer'!C48*'STR Deal Analyzer'!F48*12*0.5/'STR Deal Analyzer'!F36)-(((C3+50)*'STR Deal Analyzer'!C37*0.5+'STR Deal Analyzer'!C48*'STR Deal Analyzer'!F48*12*0.5/'STR Deal Analyzer'!F36)-((C3+50)*'STR Deal Analyzer'!C37*0.5+'STR Deal Analyzer'!C48*'STR Deal Analyzer'!F48*12*0.5/'STR Deal Analyzer'!F36)*'STR Deal Analyzer'!C45-'STR Deal Analyzer'!C48*'STR Deal Analyzer'!F48*12*0.5/'STR Deal Analyzer'!F36)*'STR Deal Analyzer'!C56)-'STR Deal Analyzer'!C60-'STR Deal Analyzer'!F60-'STR Deal Analyzer'!C61-'STR Deal Analyzer'!C72-'STR Deal Analyzer'!F61)/C5,0) | D13: =IF(C5>0,(((((C3+50)*'STR Deal Analyzer'!C37*0.55+'STR Deal Analyzer'!C48*'STR Deal Analyzer'!F48*12*0.55/'STR Deal Analyzer'!F36)-((C3+50)*'STR Deal Analyzer'!C37*0.55+'STR Deal Analyzer'!C48*'STR Deal Analyzer'!F48*12*0.55/'STR Deal Analyzer'!F36)*'STR Deal Analyzer'!C45-'STR Deal Analyzer'!C48*'STR Deal Analyzer'!F48*12*0.55/'STR Deal Analyzer'!F36)-(((C3+50)*'STR Deal Analyzer'!C37*0.55+'STR Deal Analyzer'!C48*'STR Deal Analyzer'!F48*12*0.55/'STR Deal Analyzer'!F36)-((C3+50)*'STR Deal Analyzer'!C37*0.55+'STR Deal Analyzer'!C48*'STR Deal Analyzer'!F48*12*0.55/'STR Deal Analyzer'!F36)*'STR Deal Analyzer'!C45-'STR Deal Analyzer'!C48*'STR Deal Analyzer'!F48*12*0.55/'STR Deal Analyzer'!F36)*'STR Deal Analyzer'!C56)-'STR Deal Analyzer'!C60-'STR Deal Analyzer'!F60-'STR Deal Analyzer'!C61-'STR Deal Analyzer'!C72-'STR Deal Analyzer'!F61)/C5,0) | E13: =IF(C5>0,(((((C3+50)*'STR Deal Analyzer'!C37*0.6+'STR Deal Analyzer'!C48*'STR Deal Analyzer'!F48*12*0.6/'STR Deal Analyzer'!F36)-((C3+50)*'STR Deal Analyzer'!C37*0.6+'STR Deal Analyzer'!C48*'STR Deal Analyzer'!F48*12*0.6/'STR Deal Analyzer'!F36)*'STR Deal Analyzer'!C45-'STR Deal Analyzer'!C48*'STR Deal Analyzer'!F48*12*0.6/'STR Deal Analyzer'!F36)-(((C3+50)*'STR Deal Analyzer'!C37*0.6+'STR Deal Analyzer'!C48*'STR Deal Analyzer'!F48*12*0.6/'STR Deal Analyzer'!F36)-((C3+50)*'STR Deal Analyzer'!C37*0.6+'STR Deal Analyzer'!C48*'STR Deal Analyzer'!F48*12*0.6/'STR Deal Analyzer'!F36)*'STR Deal Analyzer'!C45-'STR Deal Analyzer'!C48*'STR Deal Analyzer'!F48*12*0.6/'STR Deal Analyzer'!F36)*'STR Deal Analyzer'!C56)-'STR Deal Analyzer'!C60-'STR Deal Analyzer'!F60-'STR Deal Analyzer'!C61-'STR Deal Analyzer'!C72-'STR Deal Analyzer'!F61)/C5,0) | F13: =IF(C5>0,(((((C3+50)*'STR Deal Analyzer'!C37*0.65+'STR Deal Analyzer'!C48*'STR Deal Analyzer'!F48*12*0.65/'STR Deal Analyzer'!F36)-((C3+50)*'STR Deal Analyzer'!C37*0.65+'STR Deal Analyzer'!C48*'STR Deal Analyzer'!F48*12*0.65/'STR Deal Analyzer'!F36)*'STR Deal Analyzer'!C45-'STR Deal Analyzer'!C48*'STR Deal Analyzer'!F48*12*0.65/'STR Deal Analyzer'!F36)-(((C3+50)*'STR Deal Analyzer'!C37*0.65+'STR Deal Analyzer'!C48*'STR Deal Analyzer'!F48*12*0.65/'STR Deal Analyzer'!F36)-((C3+50)*'STR Deal Analyzer'!C37*0.65+'STR Deal Analyzer'!C48*'STR Deal Analyzer'!F48*12*0.65/'STR Deal Analyzer'!F36)*'STR Deal Analyzer'!C45-'STR Deal Analyzer'!C48*'STR Deal Analyzer'!F48*12*0.65/'STR Deal Analyzer'!F36)*'STR Deal Analyzer'!C56)-'STR Deal Analyzer'!C60-'STR Deal Analyzer'!F60-'STR Deal Analyzer'!C61-'STR Deal Analyzer'!C72-'STR Deal Analyzer'!F61)/C5,0) | G13: =IF(C5>0,(((((C3+50)*'STR Deal Analyzer'!C37*0.7+'STR Deal Analyzer'!C48*'STR Deal Analyzer'!F48*12*0.7/'STR Deal Analyzer'!F36)-((C3+50)*'STR Deal Analyzer'!C37*0.7+'STR Deal Analyzer'!C48*'STR Deal Analyzer'!F48*12*0.7/'STR Deal Analyzer'!F36)*'STR Deal Analyzer'!C45-'STR Deal Analyzer'!C48*'STR Deal Analyzer'!F48*12*0.7/'STR Deal Analyzer'!F36)-(((C3+50)*'STR Deal Analyzer'!C37*0.7+'STR Deal Analyzer'!C48*'STR Deal Analyzer'!F48*12*0.7/'STR Deal Analyzer'!F36)-((C3+50)*'STR Deal Analyzer'!C37*0.7+'STR Deal Analyzer'!C48*'STR Deal Analyzer'!F48*12*0.7/'STR Deal Analyzer'!F36)*'STR Deal Analyzer'!C45-'STR Deal Analyzer'!C48*'STR Deal Analyzer'!F48*12*0.7/'STR Deal Analyzer'!F36)*'STR Deal Analyzer'!C56)-'STR Deal Analyzer'!C60-'STR Deal Analyzer'!F60-'STR Deal Analyzer'!C61-'STR Deal Analyzer'!C72-'STR Deal Analyzer'!F61)/C5,0) | H13: =IF(C5>0,(((((C3+50)*'STR Deal Analyzer'!C37*0.75+'STR Deal Analyzer'!C48*'STR Deal Analyzer'!F48*12*0.75/'STR Deal Analyzer'!F36)-((C3+50)*'STR Deal Analyzer'!C37*0.75+'STR Deal Analyzer'!C48*'STR Deal Analyzer'!F48*12*0.75/'STR Deal Analyzer'!F36)*'STR Deal Analyzer'!C45-'STR Deal Analyzer'!C48*'STR Deal Analyzer'!F48*12*0.75/'STR Deal Analyzer'!F36)-(((C3+50)*'STR Deal Analyzer'!C37*0.75+'STR Deal Analyzer'!C48*'STR Deal Analyzer'!F48*12*0.75/'STR Deal Analyzer'!F36)-((C3+50)*'STR Deal Analyzer'!C37*0.75+'STR Deal Analyzer'!C48*'STR Deal Analyzer'!F48*12*0.75/'STR Deal Analyzer'!F36)*'STR Deal Analyzer'!C45-'STR Deal Analyzer'!C48*'STR Deal Analyzer'!F48*12*0.75/'STR Deal Analyzer'!F36)*'STR Deal Analyzer'!C56)-'STR Deal Analyzer'!C60-'STR Deal Analyzer'!F60-'STR Deal Analyzer'!C61-'STR Deal Analyzer'!C72-'STR Deal Analyzer'!F61)/C5,0) | I13: =IF(C5>0,(((((C3+50)*'STR Deal Analyzer'!C37*0.8+'STR Deal Analyzer'!C48*'STR Deal Analyzer'!F48*12*0.8/'STR Deal Analyzer'!F36)-((C3+50)*'STR Deal Analyzer'!C37*0.8+'STR Deal Analyzer'!C48*'STR Deal Analyzer'!F48*12*0.8/'STR Deal Analyzer'!F36)*'STR Deal Analyzer'!C45-'STR Deal Analyzer'!C48*'STR Deal Analyzer'!F48*12*0.8/'STR Deal Analyzer'!F36)-(((C3+50)*'STR Deal Analyzer'!C37*0.8+'STR Deal Analyzer'!C48*'STR Deal Analyzer'!F48*12*0.8/'STR Deal Analyzer'!F36)-((C3+50)*'STR Deal Analyzer'!C37*0.8+'STR Deal Analyzer'!C48*'STR Deal Analyzer'!F48*12*0.8/'STR Deal Analyzer'!F36)*'STR Deal Analyzer'!C45-'STR Deal Analyzer'!C48*'STR Deal Analyzer'!F48*12*0.8/'STR Deal Analyzer'!F36)*'STR Deal Analyzer'!C56)-'STR Deal Analyzer'!C60-'STR Deal Analyzer'!F60-'STR Deal Analyzer'!C61-'STR Deal Analyzer'!C72-'STR Deal Analyzer'!F61)/C5,0)
B14: ADR +$75 | C14: =IF(C5>0,(((((C3+75)*'STR Deal Analyzer'!C37*0.5+'STR Deal Analyzer'!C48*'STR Deal Analyzer'!F48*12*0.5/'STR Deal Analyzer'!F36)-((C3+75)*'STR Deal Analyzer'!C37*0.5+'STR Deal Analyzer'!C48*'STR Deal Analyzer'!F48*12*0.5/'STR Deal Analyzer'!F36)*'STR Deal Analyzer'!C45-'STR Deal Analyzer'!C48*'STR Deal Analyzer'!F48*12*0.5/'STR Deal Analyzer'!F36)-(((C3+75)*'STR Deal Analyzer'!C37*0.5+'STR Deal Analyzer'!C48*'STR Deal Analyzer'!F48*12*0.5/'STR Deal Analyzer'!F36)-((C3+75)*'STR Deal Analyzer'!C37*0.5+'STR Deal Analyzer'!C48*'STR Deal Analyzer'!F48*12*0.5/'STR Deal Analyzer'!F36)*'STR Deal Analyzer'!C45-'STR Deal Analyzer'!C48*'STR Deal Analyzer'!F48*12*0.5/'STR Deal Analyzer'!F36)*'STR Deal Analyzer'!C56)-'STR Deal Analyzer'!C60-'STR Deal Analyzer'!F60-'STR Deal Analyzer'!C61-'STR Deal Analyzer'!C72-'STR Deal Analyzer'!F61)/C5,0) | D14: =IF(C5>0,(((((C3+75)*'STR Deal Analyzer'!C37*0.55+'STR Deal Analyzer'!C48*'STR Deal Analyzer'!F48*12*0.55/'STR Deal Analyzer'!F36)-((C3+75)*'STR Deal Analyzer'!C37*0.55+'STR Deal Analyzer'!C48*'STR Deal Analyzer'!F48*12*0.55/'STR Deal Analyzer'!F36)*'STR Deal Analyzer'!C45-'STR Deal Analyzer'!C48*'STR Deal Analyzer'!F48*12*0.55/'STR Deal Analyzer'!F36)-(((C3+75)*'STR Deal Analyzer'!C37*0.55+'STR Deal Analyzer'!C48*'STR Deal Analyzer'!F48*12*0.55/'STR Deal Analyzer'!F36)-((C3+75)*'STR Deal Analyzer'!C37*0.55+'STR Deal Analyzer'!C48*'STR Deal Analyzer'!F48*12*0.55/'STR Deal Analyzer'!F36)*'STR Deal Analyzer'!C45-'STR Deal Analyzer'!C48*'STR Deal Analyzer'!F48*12*0.55/'STR Deal Analyzer'!F36)*'STR Deal Analyzer'!C56)-'STR Deal Analyzer'!C60-'STR Deal Analyzer'!F60-'STR Deal Analyzer'!C61-'STR Deal Analyzer'!C72-'STR Deal Analyzer'!F61)/C5,0) | E14: =IF(C5>0,(((((C3+75)*'STR Deal Analyzer'!C37*0.6+'STR Deal Analyzer'!C48*'STR Deal Analyzer'!F48*12*0.6/'STR Deal Analyzer'!F36)-((C3+75)*'STR Deal Analyzer'!C37*0.6+'STR Deal Analyzer'!C48*'STR Deal Analyzer'!F48*12*0.6/'STR Deal Analyzer'!F36)*'STR Deal Analyzer'!C45-'STR Deal Analyzer'!C48*'STR Deal Analyzer'!F48*12*0.6/'STR Deal Analyzer'!F36)-(((C3+75)*'STR Deal Analyzer'!C37*0.6+'STR Deal Analyzer'!C48*'STR Deal Analyzer'!F48*12*0.6/'STR Deal Analyzer'!F36)-((C3+75)*'STR Deal Analyzer'!C37*0.6+'STR Deal Analyzer'!C48*'STR Deal Analyzer'!F48*12*0.6/'STR Deal Analyzer'!F36)*'STR Deal Analyzer'!C45-'STR Deal Analyzer'!C48*'STR Deal Analyzer'!F48*12*0.6/'STR Deal Analyzer'!F36)*'STR Deal Analyzer'!C56)-'STR Deal Analyzer'!C60-'STR Deal Analyzer'!F60-'STR Deal Analyzer'!C61-'STR Deal Analyzer'!C72-'STR Deal Analyzer'!F61)/C5,0) | F14: =IF(C5>0,(((((C3+75)*'STR Deal Analyzer'!C37*0.65+'STR Deal Analyzer'!C48*'STR Deal Analyzer'!F48*12*0.65/'STR Deal Analyzer'!F36)-((C3+75)*'STR Deal Analyzer'!C37*0.65+'STR Deal Analyzer'!C48*'STR Deal Analyzer'!F48*12*0.65/'STR Deal Analyzer'!F36)*'STR Deal Analyzer'!C45-'STR Deal Analyzer'!C48*'STR Deal Analyzer'!F48*12*0.65/'STR Deal Analyzer'!F36)-(((C3+75)*'STR Deal Analyzer'!C37*0.65+'STR Deal Analyzer'!C48*'STR Deal Analyzer'!F48*12*0.65/'STR Deal Analyzer'!F36)-((C3+75)*'STR Deal Analyzer'!C37*0.65+'STR Deal Analyzer'!C48*'STR Deal Analyzer'!F48*12*0.65/'STR Deal Analyzer'!F36)*'STR Deal Analyzer'!C45-'STR Deal Analyzer'!C48*'STR Deal Analyzer'!F48*12*0.65/'STR Deal Analyzer'!F36)*'STR Deal Analyzer'!C56)-'STR Deal Analyzer'!C60-'STR Deal Analyzer'!F60-'STR Deal Analyzer'!C61-'STR Deal Analyzer'!C72-'STR Deal Analyzer'!F61)/C5,0) | G14: =IF(C5>0,(((((C3+75)*'STR Deal Analyzer'!C37*0.7+'STR Deal Analyzer'!C48*'STR Deal Analyzer'!F48*12*0.7/'STR Deal Analyzer'!F36)-((C3+75)*'STR Deal Analyzer'!C37*0.7+'STR Deal Analyzer'!C48*'STR Deal Analyzer'!F48*12*0.7/'STR Deal Analyzer'!F36)*'STR Deal Analyzer'!C45-'STR Deal Analyzer'!C48*'STR Deal Analyzer'!F48*12*0.7/'STR Deal Analyzer'!F36)-(((C3+75)*'STR Deal Analyzer'!C37*0.7+'STR Deal Analyzer'!C48*'STR Deal Analyzer'!F48*12*0.7/'STR Deal Analyzer'!F36)-((C3+75)*'STR Deal Analyzer'!C37*0.7+'STR Deal Analyzer'!C48*'STR Deal Analyzer'!F48*12*0.7/'STR Deal Analyzer'!F36)*'STR Deal Analyzer'!C45-'STR Deal Analyzer'!C48*'STR Deal Analyzer'!F48*12*0.7/'STR Deal Analyzer'!F36)*'STR Deal Analyzer'!C56)-'STR Deal Analyzer'!C60-'STR Deal Analyzer'!F60-'STR Deal Analyzer'!C61-'STR Deal Analyzer'!C72-'STR Deal Analyzer'!F61)/C5,0) | H14: =IF(C5>0,(((((C3+75)*'STR Deal Analyzer'!C37*0.75+'STR Deal Analyzer'!C48*'STR Deal Analyzer'!F48*12*0.75/'STR Deal Analyzer'!F36)-((C3+75)*'STR Deal Analyzer'!C37*0.75+'STR Deal Analyzer'!C48*'STR Deal Analyzer'!F48*12*0.75/'STR Deal Analyzer'!F36)*'STR Deal Analyzer'!C45-'STR Deal Analyzer'!C48*'STR Deal Analyzer'!F48*12*0.75/'STR Deal Analyzer'!F36)-(((C3+75)*'STR Deal Analyzer'!C37*0.75+'STR Deal Analyzer'!C48*'STR Deal Analyzer'!F48*12*0.75/'STR Deal Analyzer'!F36)-((C3+75)*'STR Deal Analyzer'!C37*0.75+'STR Deal Analyzer'!C48*'STR Deal Analyzer'!F48*12*0.75/'STR Deal Analyzer'!F36)*'STR Deal Analyzer'!C45-'STR Deal Analyzer'!C48*'STR Deal Analyzer'!F48*12*0.75/'STR Deal Analyzer'!F36)*'STR Deal Analyzer'!C56)-'STR Deal Analyzer'!C60-'STR Deal Analyzer'!F60-'STR Deal Analyzer'!C61-'STR Deal Analyzer'!C72-'STR Deal Analyzer'!F61)/C5,0) | I14: =IF(C5>0,(((((C3+75)*'STR Deal Analyzer'!C37*0.8+'STR Deal Analyzer'!C48*'STR Deal Analyzer'!F48*12*0.8/'STR Deal Analyzer'!F36)-((C3+75)*'STR Deal Analyzer'!C37*0.8+'STR Deal Analyzer'!C48*'STR Deal Analyzer'!F48*12*0.8/'STR Deal Analyzer'!F36)*'STR Deal Analyzer'!C45-'STR Deal Analyzer'!C48*'STR Deal Analyzer'!F48*12*0.8/'STR Deal Analyzer'!F36)-(((C3+75)*'STR Deal Analyzer'!C37*0.8+'STR Deal Analyzer'!C48*'STR Deal Analyzer'!F48*12*0.8/'STR Deal Analyzer'!F36)-((C3+75)*'STR Deal Analyzer'!C37*0.8+'STR Deal Analyzer'!C48*'STR Deal Analyzer'!F48*12*0.8/'STR Deal Analyzer'!F36)*'STR Deal Analyzer'!C45-'STR Deal Analyzer'!C48*'STR Deal Analyzer'!F48*12*0.8/'STR Deal Analyzer'!F36)*'STR Deal Analyzer'!C56)-'STR Deal Analyzer'!C60-'STR Deal Analyzer'!F60-'STR Deal Analyzer'!C61-'STR Deal Analyzer'!C72-'STR Deal Analyzer'!F61)/C5,0)
B16: Green ≥20% (ACT NOW) | Yellow 5-20% | Red <5%
